Workbook

Sheet SQL Practice Links
A1: # | B1: Section | C1: Topic | D1: Key Concepts | E1: Q1 (easiest) | F1: Q2 | G1: Q3 | H1: Q4 | I1: Q5 (hardest)
A2: 1 | B2: SQL Basics | C2: SELECT & Column Aliases | D2: SELECT *, choosing columns, AS aliases | E2: =HYPERLINK("https://www.hackerrank.com/challenges/select-all-sql/problem","Select All"&CHAR(10)&"HackerRank · Easy") -> Select All HackerRank · Easy | F2: =HYPERLINK("https://www.hackerrank.com/challenges/weather-observation-station-1/problem","Weather Observation Station 1"&CHAR(10)&"HackerRank · Easy") -> Weather Observation Station 1 HackerRank · Easy | G2: =HYPERLINK("https://www.codechef.com/practice/course/sql-case-studies-topic-wise/SQLBP01/problems/SQLPBP11","All Products (SQLPBP11)"&CHAR(10)&"CodeChef · Easy") -> All Products (SQLPBP11) CodeChef · Easy | H2: =HYPERLINK("https://www.codechef.com/learn/course/sql/SQ00LS04/problems/GSQ17","SELECT Query (GSQ17)"&CHAR(10)&"CodeChef · Easy") -> SELECT Query (GSQ17) CodeChef · Easy | I2: =HYPERLINK("https://www.codechef.com/learn/course/sql/SQ00LS08/problems/GSQ37A","Rename columns using As (GSQ37A)"&CHAR(10)&"CodeChef · Easy") -> Rename columns using As (GSQ37A) CodeChef · Easy
A3: 2 | C3: CREATE TABLE & INSERT INTO | D3: Column data types, CREATE TABLE, single- and multi-row INSERT | E3: =HYPERLINK("https://www.codechef.com/learn/course/sql/SQ00LS01/problems/GSQ04","Create table (GSQ04)"&CHAR(10)&"CodeChef · Easy") -> Create table (GSQ04) CodeChef · Easy | F3: =HYPERLINK("https://www.codechef.com/learn/course/sql/SQ00LS01/problems/GSQ07","How to insert to a table (GSQ07)"&CHAR(10)&"CodeChef · Easy") -> How to insert to a table (GSQ07) CodeChef · Easy | G3: =HYPERLINK("https://www.codechef.com/learn/course/sql/SQ00LS01/problems/GSQ05","Inserting Data into a Table (GSQ05)"&CHAR(10)&"CodeChef · Easy") -> Inserting Data into a Table (GSQ05) CodeChef · Easy | H3: =HYPERLINK("https://www.codechef.com/learn/course/sql/SQ00LS01/problems/GSQ06","Debug this query (GSQ06)"&CHAR(10)&"CodeChef · Medium") -> Debug this query (GSQ06) CodeChef · Medium | I3: =HYPERLINK("https://www.codechef.com/learn/course/sql/SQ00LS03/problems/GSQ53","Project - Customer Database (GSQ53)"&CHAR(10)&"CodeChef · Medium") -> Project - Customer Database (GSQ53) CodeChef · Medium
A4: 3 | C4: Filtering with WHERE | D4: Comparison operators, AND / OR / NOT, IS NULL / IS NOT NULL | E4: =HYPERLINK("https://leetcode.com/problems/recyclable-and-low-fat-products/","1757. Recyclable and Low Fat Products"&CHAR(10)&"LeetCode · Easy") -> 1757. Recyclable and Low Fat Products LeetCode · Easy | F4: =HYPERLINK("https://www.hackerrank.com/challenges/revising-the-select-query/problem","Revising the Select Query I"&CHAR(10)&"HackerRank · Easy") -> Revising the Select Query I HackerRank · Easy | G4: =HYPERLINK("https://www.codechef.com/practice/course/sql-case-studies-topic-wise/SQLBP01/problems/SQLPBP12","High Price of Products (SQLPBP12)"&CHAR(10)&"CodeChef · Easy") -> High Price of Products (SQLPBP12) CodeChef · Easy | H4: =HYPERLINK("https://www.codechef.com/practice/course/sql-case-studies-topic-wise/SQLBP01/problems/SQLPBP07","Handling NULL Values (SQLPBP07)"&CHAR(10)&"CodeChef · Easy") -> Handling NULL Values (SQLPBP07) CodeChef · Easy | I4: =HYPERLINK("https://leetcode.com/problems/find-customer-referee/","584. Find Customer Referee"&CHAR(10)&"LeetCode · Medium") -> 584. Find Customer Referee LeetCode · Medium
A5: 4 | C5: DISTINCT, ORDER BY & LIMIT | D5: Removing duplicates, sorting (ASC / DESC, several keys), top-N with LIMIT | E5: =HYPERLINK("https://www.codechef.com/practice/course/sql-case-studies-topic-wise/SQLBP01/problems/SQLPBP13","Distinct Companies (SQLPBP13)"&CHAR(10)&"CodeChef · Easy") -> Distinct Companies (SQLPBP13) CodeChef · Easy | F5: =HYPERLINK("https://www.hackerrank.com/challenges/name-of-employees/problem","Employee Names"&CHAR(10)&"HackerRank · Easy") -> Employee Names HackerRank · Easy | G5: =HYPERLINK("https://leetcode.com/problems/article-views-i/","1148. Article Views I"&CHAR(10)&"LeetCode · Easy") -> 1148. Article Views I LeetCode · Easy | H5: =HYPERLINK("https://www.hackerrank.com/challenges/salary-of-employees/problem","Employee Salaries"&CHAR(10)&"HackerRank · Medium") -> Employee Salaries HackerRank · Medium | I5: =HYPERLINK("https://www.codechef.com/learn/course/sql/BEGSQLPR/problems/RSMSPR03C","Task-3C Data Retrieval Using Queries (RSMSPR03C)"&CHAR(10)&"CodeChef · Medium") -> Task-3C Data Retrieval Using Queries (RSMSPR03C) CodeChef · Medium
A6: 5 | C6: BETWEEN, IN & LIKE | D6: Ranges, value lists, wildcard patterns (% and _), NOT LIKE | E6: =HYPERLINK("https://www.codechef.com/learn/course/sql/SQ00LS04/problems/GSQ19A","BETWEEN (GSQ19A)"&CHAR(10)&"CodeChef · Easy") -> BETWEEN (GSQ19A) CodeChef · Easy | F6: =HYPERLINK("https://www.codechef.com/learn/course/sql/SQ00LS05/problems/GSQ26","Practice - Filter with multiple Like patterns (GSQ26)"&CHAR(10)&"CodeChef · Easy") -> Practice - Filter with multiple Like patterns (GSQ26) CodeChef · Easy | G6: =HYPERLINK("https://leetcode.com/problems/patients-with-a-condition/","1527. Patients With a Condition"&CHAR(10)&"LeetCode · Medium") -> 1527. Patients With a Condition LeetCode · Medium | H6: =HYPERLINK("https://www.hackerrank.com/challenges/weather-observation-station-6/problem","Weather Observation Station 6"&CHAR(10)&"HackerRank · Medium") -> Weather Observation Station 6 HackerRank · Medium | I6: =HYPERLINK("https://www.hackerrank.com/challenges/weather-observation-station-12/problem","Weather Observation Station 12"&CHAR(10)&"HackerRank · Challenging") -> Weather Observation Station 12 HackerRank · Challenging
A7: 6 | B7: Functions & Aggregation | C7: String Functions | D7: LENGTH, UPPER / LOWER, SUBSTRING / LEFT / RIGHT, CONCAT, REPLACE, REGEXP | E7: =HYPERLINK("https://leetcode.com/problems/invalid-tweets/","1683. Invalid Tweets"&CHAR(10)&"LeetCode · Easy") -> 1683. Invalid Tweets LeetCode · Easy | F7: =HYPERLINK("https://www.hackerrank.com/challenges/more-than-75-marks/problem","Higher Than 75 Marks"&CHAR(10)&"HackerRank · Easy") -> Higher Than 75 Marks HackerRank · Easy | G7: =HYPERLINK("https://leetcode.com/problems/fix-names-in-a-table/","1667. Fix Names in a Table"&CHAR(10)&"LeetCode · Medium") -> 1667. Fix Names in a Table LeetCode · Medium | H7: =HYPERLINK("https://www.hackerrank.com/challenges/weather-observation-station-5/problem","Weather Observation Station 5"&CHAR(10)&"HackerRank · Medium") -> Weather Observation Station 5 HackerRank · Medium | I7: =HYPERLINK("https://leetcode.com/problems/find-users-with-valid-e-mails/","1517. Find Users With Valid E-Mails"&CHAR(10)&"LeetCode · Challenging") -> 1517. Find Users With Valid E-Mails LeetCode · Challenging
A8: 7 | C8: Aggregate Functions | D8: COUNT, SUM, AVG, MIN, MAX (with WHERE) | E8: =HYPERLINK("https://www.hackerrank.com/challenges/revising-aggregations-the-count-function/problem","Revising Aggregations - The Count Function"&CHAR(10)&"HackerRank · Easy") -> Revising Aggregations - The Count Function HackerRank · Easy | F8: =HYPERLINK("https://www.codechef.com/practice/course/sql-case-studies-topic-wise/SQLBP01/problems/SQLPBP02","Fiction Collection Size (SQLPBP02)"&CHAR(10)&"CodeChef · Easy") -> Fiction Collection Size (SQLPBP02) CodeChef · Easy | G8: =HYPERLINK("https://www.codechef.com/practice/course/sql-case-studies-topic-wise/SQLBP01/problems/SQLPBP14","Average Salary (SQLPBP14)"&CHAR(10)&"CodeChef · Easy") -> Average Salary (SQLPBP14) CodeChef · Easy | H8: =HYPERLINK("https://www.codechef.com/learn/course/sql/SQ00LS09/problems/GSQ44","Problem - SUM() and AVG() (GSQ44)"&CHAR(10)&"CodeChef · Medium") -> Problem - SUM() and AVG() (GSQ44) CodeChef · Medium | I8: =HYPERLINK("https://www.hackerrank.com/challenges/population-density-difference/problem","Population Density Difference"&CHAR(10)&"HackerRank · Medium") -> Population Density Difference HackerRank · Medium
A9: 8 | C9: Numeric Functions | D9: ROUND, CEIL / FLOOR, MOD, POWER / SQRT | E9: =HYPERLINK("https://www.hackerrank.com/challenges/weather-observation-station-3/problem","Weather Observation Station 3"&CHAR(10)&"HackerRank · Easy") -> Weather Observation Station 3 HackerRank · Easy | F9: =HYPERLINK("https://leetcode.com/problems/not-boring-movies/","620. Not Boring Movies"&CHAR(10)&"LeetCode · Easy") -> 620. Not Boring Movies LeetCode · Easy | G9: =HYPERLINK("https://www.codechef.com/learn/course/sql/SQ00LS08/problems/GSQ41","Problem-ROUND() (GSQ41)"&CHAR(10)&"CodeChef · Easy") -> Problem-ROUND() (GSQ41) CodeChef · Easy | H9: =HYPERLINK("https://www.hackerrank.com/challenges/the-blunder/problem","The Blunder"&CHAR(10)&"HackerRank · Medium") -> The Blunder HackerRank · Medium | I9: =HYPERLINK("https://www.hackerrank.com/challenges/weather-observation-station-19/problem","Weather Observation Station 19"&CHAR(10)&"HackerRank · Challenging") -> Weather Observation Station 19 HackerRank · Challenging
A10: 9 | C10: GROUP BY | D10: Grouping by one or more columns, COUNT(DISTINCT), GROUP_CONCAT / STRING_AGG | E10: =HYPERLINK("https://leetcode.com/problems/number-of-unique-subjects-taught-by-each-teacher/","2356. Number of Unique Subjects Taught by Each Teacher"&CHAR(10)&"LeetCode · Easy") -> 2356. Number of Unique Subjects Taught by Each Teacher LeetCode · Easy | F10: =HYPERLINK("https://www.codechef.com/practice/course/sql-case-studies-topic-wise/SQLBP01/problems/SQLPBP09","Department of Each Employee (SQLPBP09)"&CHAR(10)&"CodeChef · Easy") -> Department of Each Employee (SQLPBP09) CodeChef · Easy | G10: =HYPERLINK("https://leetcode.com/problems/find-total-time-spent-by-each-employee/","1741. Find Total Time Spent by Each Employee"&CHAR(10)&"LeetCode · Easy") -> 1741. Find Total Time Spent by Each Employee LeetCode · Easy | H10: =HYPERLINK("https://leetcode.com/problems/group-sold-products-by-the-date/","1484. Group Sold Products By The Date"&CHAR(10)&"LeetCode · Medium") -> 1484. Group Sold Products By The Date LeetCode · Medium | I10: =HYPERLINK("https://www.hackerrank.com/challenges/the-pads/problem","The PADS"&CHAR(10)&"HackerRank · Challenging") -> The PADS HackerRank · Challenging
A11: 10 | C11: HAVING | D11: Filtering groups, WHERE vs HAVING | E11: =HYPERLINK("https://leetcode.com/problems/duplicate-emails/","182. Duplicate Emails"&CHAR(10)&"LeetCode · Easy") -> 182. Duplicate Emails LeetCode · Easy | F11: =HYPERLINK("https://leetcode.com/problems/classes-with-at-least-5-students/","596. Classes With at Least 5 Students"&CHAR(10)&"LeetCode · Easy") -> 596. Classes With at Least 5 Students LeetCode · Easy | G11: =HYPERLINK("https://www.codechef.com/learn/course/sql/SQ00LS09/problems/GSQ46","Having (GSQ46)"&CHAR(10)&"CodeChef · Medium") -> Having (GSQ46) CodeChef · Medium | H11: =HYPERLINK("https://leetcode.com/problems/actors-and-directors-who-cooperated-at-least-three-times/","1050. Actors and Directors Who Cooperated At Least Three Times"&CHAR(10)&"LeetCode · Medium") -> 1050. Actors and Directors Who Cooperated At Least Three Times LeetCode · Medium | I11: =HYPERLINK("https://www.codechef.com/learn/course/sql/SQ00LS09/problems/GSQ47","Problem-Group By & Having (GSQ47)"&CHAR(10)&"CodeChef · Challenging") -> Problem-Group By & Having (GSQ47) CodeChef · Challenging
A12: 11 | B12: Conditional Logic & Dates | C12: CASE Expressions | D12: Searched CASE, CASE in SELECT / ORDER BY, CASE inside aggregates | E12: =HYPERLINK("https://www.hackerrank.com/challenges/what-type-of-triangle/problem","Type of Triangle"&CHAR(10)&"HackerRank · Easy") -> Type of Triangle HackerRank · Easy | F12: =HYPERLINK("https://leetcode.com/problems/triangle-judgement/","610. Triangle Judgement"&CHAR(10)&"LeetCode · Easy") -> 610. Triangle Judgement LeetCode · Easy | G12: =HYPERLINK("https://leetcode.com/problems/calculate-special-bonus/","1873. Calculate Special Bonus"&CHAR(10)&"LeetCode · Medium") -> 1873. Calculate Special Bonus LeetCode · Medium | H12: =HYPERLINK("https://www.codechef.com/learn/course/sql-intermediate/SQ00BS08/problems/GSQ81","Case - When (GSQ81)"&CHAR(10)&"CodeChef · Medium") -> Case - When (GSQ81) CodeChef · Medium | I12: =HYPERLINK("https://www.codechef.com/learn/course/sql-intermediate/SQ00BS08/problems/GSQ83","Sum using Case (GSQ83)"&CHAR(10)&"CodeChef · Medium") -> Sum using Case (GSQ83) CodeChef · Medium
A13: 12 | C13: Date & Time Functions | D13: YEAR / MONTH, DATE_FORMAT / strftime, DATEDIFF / JULIANDAY, date ranges | E13: =HYPERLINK("https://leetcode.com/problems/user-activity-for-the-past-30-days-i/","1141. User Activity for the Past 30 Days I"&CHAR(10)&"LeetCode · Easy") -> 1141. User Activity for the Past 30 Days I LeetCode · Easy | F13: =HYPERLINK("https://leetcode.com/problems/the-latest-login-in-2020/","1890. The Latest Login in 2020"&CHAR(10)&"LeetCode · Easy") -> 1890. The Latest Login in 2020 LeetCode · Easy | G13: =HYPERLINK("https://www.codechef.com/learn/course/sql/BEGSQLPR/problems/RSMSPR06C","Task-6C Aggregations & Grouping (RSMSPR06C)"&CHAR(10)&"CodeChef · Medium") -> Task-6C Aggregations & Grouping (RSMSPR06C) CodeChef · Medium | H13: =HYPERLINK("https://www.codechef.com/learn/course/sql/BEGSQLPR/problems/RSMSPR08","Task-8 Date Functions (RSMSPR08)"&CHAR(10)&"CodeChef · Medium") -> Task-8 Date Functions (RSMSPR08) CodeChef · Medium | I13: =HYPERLINK("https://leetcode.com/problems/monthly-transactions-i/","1193. Monthly Transactions I"&CHAR(10)&"LeetCode · Challenging") -> 1193. Monthly Transactions I LeetCode · Challenging
A14: 13 | C14: Pivoting & Conditional Aggregation | D14: SUM / AVG / COUNT over CASE, rows-to-columns reports, ratios and percentages | E14: =HYPERLINK("https://leetcode.com/problems/reformat-department-table/","1179. Reformat Department Table"&CHAR(10)&"LeetCode · Easy") -> 1179. Reformat Department Table LeetCode · Easy | F14: =HYPERLINK("https://leetcode.com/problems/queries-quality-and-percentage/","1211. Queries Quality and Percentage"&CHAR(10)&"LeetCode · Easy") -> 1211. Queries Quality and Percentage LeetCode · Easy | G14: =HYPERLINK("https://www.codechef.com/learn/course/sql-intermediate/SQ00BS08/problems/GSQ84","Combining Aggregates (GSQ84)"&CHAR(10)&"CodeChef · Medium") -> Combining Aggregates (GSQ84) CodeChef · Medium | H14: =HYPERLINK("https://leetcode.com/problems/capital-gainloss/","1393. Capital Gain/Loss"&CHAR(10)&"LeetCode · Medium") -> 1393. Capital Gain/Loss LeetCode · Medium | I14: =HYPERLINK("https://leetcode.com/problems/odd-and-even-transactions/","3220. Odd and Even Transactions"&CHAR(10)&"LeetCode · Challenging") -> 3220. Odd and Even Transactions LeetCode · Challenging
A15: 14 | B15: Data Modification & Schema | C15: UPDATE & DELETE | D15: UPDATE ... SET ... WHERE, DELETE FROM ... WHERE, UPDATE with CASE | E15: =HYPERLINK("https://www.codechef.com/learn/course/sql/SQ00LS02/problems/GSQ11","Practice Problem - Update table (GSQ11)"&CHAR(10)&"CodeChef · Easy") -> Practice Problem - Update table (GSQ11) CodeChef · Easy | F15: =HYPERLINK("https://www.codechef.com/learn/course/sql/SQ00LS03/problems/GSQ56","Practice - Delete Single Record (GSQ56)"&CHAR(10)&"CodeChef · Easy") -> Practice - Delete Single Record (GSQ56) CodeChef · Easy | G15: =HYPERLINK("https://www.codechef.com/learn/course/sql/SQ00LS02/problems/GSQ14","Practice - Delete From (GSQ14)"&CHAR(10)&"CodeChef · Easy") -> Practice - Delete From (GSQ14) CodeChef · Easy | H15: =HYPERLINK("https://www.codechef.com/learn/course/sql/BEGSQLPR/problems/RSMSPR04C","Task-4C Data Modification (Update and Alter) (RSMSPR04C)"&CHAR(10)&"CodeChef · Medium") -> Task-4C Data Modification (Update and Alter) (RSMSPR04C) CodeChef · Medium | I15: =HYPERLINK("https://leetcode.com/problems/swap-sex-of-employees/","627. Swap Sex of Employees"&CHAR(10)&"LeetCode · Medium") -> 627. Swap Sex of Employees LeetCode · Medium
A16: 15 | C16: ALTER TABLE & Constraints | D16: ADD COLUMN, DEFAULT, PRIMARY KEY, UNIQUE, NOT NULL, CHECK, FOREIGN KEY | E16: =HYPERLINK("https://www.codechef.com/learn/course/sql/SQ00LS02/problems/GSQ10","Practice Problem - Alter table (GSQ10)"&CHAR(10)&"CodeChef · Easy") -> Practice Problem - Alter table (GSQ10) CodeChef · Easy | F16: =HYPERLINK("https://www.codechef.com/learn/course/sql/SQ00LS02/problems/GSQ13","Constraints (GSQ13)"&CHAR(10)&"CodeChef · Easy") -> Constraints (GSQ13) CodeChef · Easy | G16: =HYPERLINK("https://www.codechef.com/learn/course/sql/SQ00LS03/problems/GSQ57","Practice - Create Table with Constraints (GSQ57)"&CHAR(10)&"CodeChef · Medium") -> Practice - Create Table with Constraints (GSQ57) CodeChef · Medium | H16: =HYPERLINK("https://www.codechef.com/learn/course/sql-intermediate/SQ00BS02/problems/SQLKEY01","Foreign Key and Unique Key (SQLKEY01)"&CHAR(10)&"CodeChef · Medium") -> Foreign Key and Unique Key (SQLKEY01) CodeChef · Medium | I16: =HYPERLINK("https://www.codechef.com/learn/course/sql/BEGSQLPR/problems/RSMSPR01","Task-1 Design the Database Schema- Tables & Fields (RSMSPR01)"&CHAR(10)&"CodeChef · Challenging") -> Task-1 Design the Database Schema- Tables & Fields (RSMSPR01) CodeChef · Challenging
A17: 16 | B17: Joins | C17: INNER JOIN | D17: Equi-joins, multi-table joins, non-equi joins | E17: =HYPERLINK("https://leetcode.com/problems/product-sales-analysis-i/","1068. Product Sales Analysis I"&CHAR(10)&"LeetCode · Easy") -> 1068. Product Sales Analysis I LeetCode · Easy | F17: =HYPERLINK("https://www.hackerrank.com/challenges/african-cities/problem","African Cities"&CHAR(10)&"HackerRank · Easy") -> African Cities HackerRank · Easy | G17: =HYPERLINK("https://www.codechef.com/learn/course/sql-intermediate/SQ00BS01/problems/GSQ62","Inner Joins (GSQ62)"&CHAR(10)&"CodeChef · Easy") -> Inner Joins (GSQ62) CodeChef · Easy | H17: =HYPERLINK("https://www.hackerrank.com/challenges/the-report/problem","The Report"&CHAR(10)&"HackerRank · Medium") -> The Report HackerRank · Medium | I17: =HYPERLINK("https://www.hackerrank.com/challenges/full-score/problem","Top Competitors"&CHAR(10)&"HackerRank · Challenging") -> Top Competitors HackerRank · Challenging
A18: 17 | C18: LEFT / RIGHT / FULL OUTER JOIN | D18: Keeping unmatched rows, IS NULL anti-join, IFNULL / COALESCE | E18: =HYPERLINK("https://leetcode.com/problems/combine-two-tables/","175. Combine Two Tables"&CHAR(10)&"LeetCode · Easy") -> 175. Combine Two Tables LeetCode · Easy | F18: =HYPERLINK("https://leetcode.com/problems/replace-employee-id-with-the-unique-identifier/","1378. Replace Employee ID With The Unique Identifier"&CHAR(10)&"LeetCode · Easy") -> 1378. Replace Employee ID With The Unique Identifier LeetCode · Easy | G18: =HYPERLINK("https://www.codechef.com/learn/course/sql-intermediate/SQ00BS01/problems/ASQL01B","Full Outer Joins (ASQL01B)"&CHAR(10)&"CodeChef · Medium") -> Full Outer Joins (ASQL01B) CodeChef · Medium | H18: =HYPERLINK("https://leetcode.com/problems/customer-who-visited-but-did-not-make-any-transactions/","1581. Customer Who Visited but Did Not Make Any Transactions"&CHAR(10)&"LeetCode · Medium") -> 1581. Customer Who Visited but Did Not Make Any Transactions LeetCode · Medium | I18: =HYPERLINK("https://leetcode.com/problems/average-selling-price/","1251. Average Selling Price"&CHAR(10)&"LeetCode · Challenging") -> 1251. Average Selling Price LeetCode · Challenging
A19: 18 | C19: SELF JOIN & CROSS JOIN | D19: Table aliases, comparing rows of the same table, Cartesian product | E19: =HYPERLINK("https://leetcode.com/problems/employees-earning-more-than-their-managers/","181. Employees Earning More Than Their Managers"&CHAR(10)&"LeetCode · Easy") -> 181. Employees Earning More Than Their Managers LeetCode · Easy | F19: =HYPERLINK("https://www.codechef.com/learn/course/sql-intermediate/SQ00BS01/problems/ASQL01C","Self Joins (ASQL01C)"&CHAR(10)&"CodeChef · Easy") -> Self Joins (ASQL01C) CodeChef · Easy | G19: =HYPERLINK("https://leetcode.com/problems/students-and-examinations/","1280. Students and Examinations"&CHAR(10)&"LeetCode · Medium") -> 1280. Students and Examinations LeetCode · Medium | H19: =HYPERLINK("https://leetcode.com/problems/rising-temperature/","197. Rising Temperature"&CHAR(10)&"LeetCode · Medium") -> 197. Rising Temperature LeetCode · Medium | I19: =HYPERLINK("https://www.hackerrank.com/challenges/symmetric-pairs/problem","Symmetric Pairs"&CHAR(10)&"HackerRank · Challenging") -> Symmetric Pairs HackerRank · Challenging
A20: 19 | B20: Subqueries & Set Operations | C20: Subqueries | D20: Scalar subqueries, IN / NOT IN, subqueries in HAVING | E20: =HYPERLINK("https://leetcode.com/problems/employees-whose-manager-left-the-company/","1978. Employees Whose Manager Left the Company"&CHAR(10)&"LeetCode · Easy") -> 1978. Employees Whose Manager Left the Company LeetCode · Easy | F20: =HYPERLINK("https://www.codechef.com/learn/course/sql-intermediate/SQ00BS04/problems/GSQ71","Problem - Non-Correlated Subqueries (GSQ71)"&CHAR(10)&"CodeChef · Easy") -> Problem - Non-Correlated Subqueries (GSQ71) CodeChef · Easy | G20: =HYPERLINK("https://www.hackerrank.com/challenges/binary-search-tree-1/problem","Binary Tree Nodes"&CHAR(10)&"HackerRank · Medium") -> Binary Tree Nodes HackerRank · Medium | H20: =HYPERLINK("https://leetcode.com/problems/second-highest-salary/","176. Second Highest Salary"&CHAR(10)&"LeetCode · Medium") -> 176. Second Highest Salary LeetCode · Medium | I20: =HYPERLINK("https://leetcode.com/problems/customers-who-bought-all-products/","1045. Customers Who Bought All Products"&CHAR(10)&"LeetCode · Challenging") -> 1045. Customers Who Bought All Products LeetCode · Challenging
A21: 20 | C21: Correlated Subqueries & EXISTS | D21: Per-row subqueries, EXISTS / NOT EXISTS | E21: =HYPERLINK("https://leetcode.com/problems/customers-who-never-order/","183. Customers Who Never Order"&CHAR(10)&"LeetCode · Easy") -> 183. Customers Who Never Order LeetCode · Easy | F21: =HYPERLINK("https://leetcode.com/problems/department-highest-salary/","184. Department Highest Salary"&CHAR(10)&"LeetCode · Medium") -> 184. Department Highest Salary LeetCode · Medium | G21: =HYPERLINK("https://leetcode.com/problems/product-price-at-a-given-date/","1164. Product Price at a Given Date"&CHAR(10)&"LeetCode · Medium") -> 1164. Product Price at a Given Date LeetCode · Medium | H21: =HYPERLINK("https://www.hackerrank.com/challenges/harry-potter-and-wands/problem","Ollivander's Inventory"&CHAR(10)&"HackerRank · Challenging") -> Ollivander's Inventory HackerRank · Challenging | I21: =HYPERLINK("https://leetcode.com/problems/department-top-three-salaries/","185. Department Top Three Salaries"&CHAR(10)&"LeetCode · Challenging") -> 185. Department Top Three Salaries LeetCode · Challenging
A22: 21 | C22: Set Operations | D22: UNION / UNION ALL, INTERSECT, EXCEPT | E22: =HYPERLINK("https://www.codechef.com/learn/course/sql-intermediate/SQ00BS02/problems/GSQ66","Union (GSQ66)"&CHAR(10)&"CodeChef · Easy") -> Union (GSQ66) CodeChef · Easy | F22: =HYPERLINK("https://www.codechef.com/learn/course/sql-intermediate/SQ00BS06/problems/GSQ77","Except (GSQ77)"&CHAR(10)&"CodeChef · Easy") -> Except (GSQ77) CodeChef · Easy | G22: =HYPERLINK("https://leetcode.com/problems/rearrange-products-table/","1795. Rearrange Products Table"&CHAR(10)&"LeetCode · Medium") -> 1795. Rearrange Products Table LeetCode · Medium | H22: =HYPERLINK("https://leetcode.com/problems/count-salary-categories/","1907. Count Salary Categories"&CHAR(10)&"LeetCode · Medium") -> 1907. Count Salary Categories LeetCode · Medium | I22: =HYPERLINK("https://leetcode.com/problems/movie-rating/","1341. Movie Rating"&CHAR(10)&"LeetCode · Challenging") -> 1341. Movie Rating LeetCode · Challenging
A23: 22 | B23: Advanced SQL | C23: Common Table Expressions (WITH) | D23: Named subqueries, multi-step queries, derived tables | E23: =HYPERLINK("https://www.codechef.com/learn/course/sql-intermediate/SQ00BS03/problems/GSQ68F","Project - Temporary table with Join (GSQ68F)"&CHAR(10)&"CodeChef · Medium") -> Project - Temporary table with Join (GSQ68F) CodeChef · Medium | F23: =HYPERLINK("https://leetcode.com/problems/product-sales-analysis-iii/","1070. Product Sales Analysis III"&CHAR(10)&"LeetCode · Medium") -> 1070. Product Sales Analysis III LeetCode · Medium | G23: =HYPERLINK("https://www.hackerrank.com/challenges/contest-leaderboard/problem","Contest Leaderboard"&CHAR(10)&"HackerRank · Medium") -> Contest Leaderboard HackerRank · Medium | H23: =HYPERLINK("https://leetcode.com/problems/investments-in-2016/","585. Investments in 2016"&CHAR(10)&"LeetCode · Challenging") -> 585. Investments in 2016 LeetCode · Challenging | I23: =HYPERLINK("https://www.hackerrank.com/challenges/interviews/problem","Interviews"&CHAR(10)&"HackerRank · Challenging") -> Interviews HackerRank · Challenging
A24: 23 | C24: Window Functions – Ranking | D24: ROW_NUMBER, RANK, DENSE_RANK, PARTITION BY | E24: =HYPERLINK("https://leetcode.com/problems/rank-scores/","178. Rank Scores"&CHAR(10)&"LeetCode · Easy") -> 178. Rank Scores LeetCode · Easy | F24: =HYPERLINK("https://www.codechef.com/learn/course/sql-intermediate/JJTST2/problems/ASQLPR112","Task-11 Rank Doctors Based on Patient Feedback (ASQLPR112)"&CHAR(10)&"CodeChef · Medium") -> Task-11 Rank Doctors Based on Patient Feedback (ASQLPR112) CodeChef · Medium | G24: =HYPERLINK("https://www.codechef.com/learn/course/sql-intermediate/JJTST2/problems/ASQLPR113","Task-12 Analyze Treatment Trends Per Department (ASQLPR113)"&CHAR(10)&"CodeChef · Medium") -> Task-12 Analyze Treatment Trends Per Department (ASQLPR113) CodeChef · Medium | H24: =HYPERLINK("https://www.hackerrank.com/challenges/occupations/problem","Occupations"&CHAR(10)&"HackerRank · Challenging") -> Occupations HackerRank · Challenging | I24: =HYPERLINK("https://leetcode.com/problems/seasonal-sales-analysis/","3564. Seasonal Sales Analysis"&CHAR(10)&"LeetCode · Challenging") -> 3564. Seasonal Sales Analysis LeetCode · Challenging
A25: 24 | C25: Window Functions – LAG / LEAD & Running Totals | D25: LAG / LEAD, SUM() OVER, window frames (ROWS BETWEEN), gaps and islands | E25: =HYPERLINK("https://leetcode.com/problems/consecutive-numbers/","180. Consecutive Numbers"&CHAR(10)&"LeetCode · Medium") -> 180. Consecutive Numbers LeetCode · Medium | F25: =HYPERLINK("https://leetcode.com/problems/last-person-to-fit-in-the-bus/","1204. Last Person to Fit in the Bus"&CHAR(10)&"LeetCode · Medium") -> 1204. Last Person to Fit in the Bus LeetCode · Medium | G25: =HYPERLINK("https://leetcode.com/problems/restaurant-growth/","1321. Restaurant Growth"&CHAR(10)&"LeetCode · Medium") -> 1321. Restaurant Growth LeetCode · Medium | H25: =HYPERLINK("https://www.hackerrank.com/challenges/sql-projects/problem","SQL Project Planning"&CHAR(10)&"HackerRank · Challenging") -> SQL Project Planning HackerRank · Challenging | I25: =HYPERLINK("https://leetcode.com/problems/human-traffic-of-stadium/","601. Human Traffic of Stadium"&CHAR(10)&"LeetCode · Challenging") -> 601. Human Traffic of Stadium LeetCode · Challenging
A26: 25 | C26: Recursive CTEs | D26: WITH RECURSIVE, generating rows / numbers, walking hierarchies | E26: =HYPERLINK("https://www.hackerrank.com/challenges/draw-the-triangle-1/problem","Draw The Triangle 1"&CHAR(10)&"HackerRank · Easy") -> Draw The Triangle 1 HackerRank · Easy | F26: =HYPERLINK("https://www.hackerrank.com/challenges/draw-the-triangle-2/problem","Draw The Triangle 2"&CHAR(10)&"HackerRank · Easy") -> Draw The Triangle 2 HackerRank · Easy | G26: =HYPERLINK("https://www.hackerrank.com/challenges/print-prime-numbers/problem","Print Prime Numbers"&CHAR(10)&"HackerRank · Medium") -> Print Prime Numbers HackerRank · Medium | H26: =HYPERLINK("https://leetcode.com/problems/analyze-organization-hierarchy/","3482. Analyze Organization Hierarchy"&CHAR(10)&"LeetCode · Challenging") -> 3482. Analyze Organization Hierarchy LeetCode · Challenging | I26: Not available – see Validation Report
A27: 26 | C27: Stored Functions & Procedures | D27: CREATE FUNCTION, parameters, RETURN | E27: =HYPERLINK("https://leetcode.com/problems/nth-highest-salary/","177. Nth Highest Salary"&CHAR(10)&"LeetCode · Medium") -> 177. Nth Highest Salary LeetCode · Medium | F27: Not available – see Validation Report | G27: Not available – see Validation Report | H27: Not available – see Validation Report | I27: Not available – see Validation Report
B29: Legend
B30: LeetCode problem | D30: Each cell links to the problem. The second line shows the platform and the level within the topic (Q1 easiest → Q5 hardest). Every problem needs only the current topic and earlier ones. Full details are in 'Question Bank Details'.
B31: HackerRank challenge
B32: CodeChef problem
B33: Not available – see Validation Report

Sheet Question Bank Details
A1: # | B1: Section | C1: Topic | D1: Q# | E1: Question Title | F1: Platform | G1: Difficulty | H1: Problem URL | I1: Free Access | J1: Primary Concept | K1: Prerequisite Concepts | L1: Topic Boundary Verified | M1: Status | N1: Counts as Valid | O1: Matrix Cell | P1: Notes (SQL engine / context)
A2: 1 | B2: SQL Basics | C2: SELECT & Column Aliases | D2: Q1 | E2: Select All | F2: HackerRank | G2: Easy (HackerRank: Easy) | H2: =HYPERLINK("https://www.hackerrank.com/challenges/select-all-sql/problem","https://www.hackerrank.com/challenges/select-all-sql/problem") -> https://www.hackerrank.com/challenges/select-all-sql/problem | I2: Yes – free; free HackerRank account to submit | J2: SELECT * (all columns) | K2: None (first topic) | L2: Yes – SELECT * FROM CITY | M2: Added (verified) | N2: =IF(M2="Added (verified)","Yes","No") -> Yes | O2: E2 | P2: Engines: MySQL, MS SQL Server, Oracle, DB2.
A3: 1 | B3: SQL Basics | C3: SELECT & Column Aliases | D3: Q2 | E3: Weather Observation Station 1 | F3: HackerRank | G3: Easy (HackerRank: Easy) | H3: =HYPERLINK("https://www.hackerrank.com/challenges/weather-observation-station-1/problem","https://www.hackerrank.com/challenges/weather-observation-station-1/problem") -> https://www.hackerrank.com/challenges/weather-observation-station-1/problem | I3: Yes – free; free HackerRank account to submit | J3: Selecting specific columns | K3: None (first topic) | L3: Yes – SELECT CITY, STATE FROM STATION | M3: Added (verified) | N3: =IF(M3="Added (verified)","Yes","No") -> Yes | O3: F2 | P3: Engines: MySQL, MS SQL Server, Oracle, DB2.
A4: 1 | B4: SQL Basics | C4: SELECT & Column Aliases | D4: Q3 | E4: All Products (SQLPBP11) | F4: CodeChef | G4: Easy (CodeChef: easy) | H4: =HYPERLINK("https://www.codechef.com/practice/course/sql-case-studies-topic-wise/SQLBP01/problems/SQLPBP11","https://www.codechef.com/practice/course/sql-case-studies-topic-wise/SQLBP01/problems/SQLPBP11") -> https://www.codechef.com/practice/course/sql-case-studies-topic-wise/SQLBP01/problems/SQLPBP11 | I4: Yes – free (non-Pro) module of CodeChef 'SQL Practice Queries'; free account to submit | J4: SELECT * from a named table | K4: None (first topic) | L4: Yes – outputs the whole Products table | M4: Added (verified) | N4: =IF(M4="Added (verified)","Yes","No") -> Yes | O4: G2 | P4: Module 'Practice Basic Commands'. MySQL syntax.
A5: 1 | B5: SQL Basics | C5: SELECT & Column Aliases | D5: Q4 | E5: SELECT Query (GSQ17) | F5: CodeChef | G5: Easy (CodeChef: easy) | H5: =HYPERLINK("https://www.codechef.com/learn/course/sql/SQ00LS04/problems/GSQ17","https://www.codechef.com/learn/course/sql/SQ00LS04/problems/GSQ17") -> https://www.codechef.com/learn/course/sql/SQ00LS04/problems/GSQ17 | I5: Yes – free (non-Pro) lesson of CodeChef 'Learn SQL'; free account to submit | J5: Selecting specific columns | K5: None (first topic) | L5: Yes – SELECT passenger_name, gender FROM flights | M5: Added (verified) | N5: =IF(M5="Added (verified)","Yes","No") -> Yes | O5: H2 | P5: Runs on SQLite.
A6: 1 | B6: SQL Basics | C6: SELECT & Column Aliases | D6: Q5 | E6: Rename columns using As (GSQ37A) | F6: CodeChef | G6: Easy (CodeChef: easy) | H6: =HYPERLINK("https://www.codechef.com/learn/course/sql/SQ00LS08/problems/GSQ37A","https://www.codechef.com/learn/course/sql/SQ00LS08/problems/GSQ37A") -> https://www.codechef.com/learn/course/sql/SQ00LS08/problems/GSQ37A | I6: Yes – free (non-Pro) lesson of CodeChef 'Learn SQL'; free account to submit | J6: Column aliases with AS | K6: Selecting columns | L6: Yes – three columns renamed with AS; no filtering or functions | M6: Added (verified) | N6: =IF(M6="Added (verified)","Yes","No") -> Yes | O6: I2 | P6: Runs on SQLite.
A7: 2 | B7: SQL Basics | C7: CREATE TABLE & INSERT INTO | D7: Q1 | E7: Create table (GSQ04) | F7: CodeChef | G7: Easy (CodeChef: easy) | H7: =HYPERLINK("https://www.codechef.com/learn/course/sql/SQ00LS01/problems/GSQ04","https://www.codechef.com/learn/course/sql/SQ00LS01/problems/GSQ04") -> https://www.codechef.com/learn/course/sql/SQ00LS01/problems/GSQ04 | I7: Yes – free (non-Pro) lesson of CodeChef 'Learn SQL'; free account to submit | J7: CREATE TABLE with column data types | K7: None | L7: Yes – one CREATE TABLE statement | M7: Added (verified) | N7: =IF(M7="Added (verified)","Yes","No") -> Yes | O7: E3 | P7: Runs on SQLite.
A8: 2 | B8: SQL Basics | C8: CREATE TABLE & INSERT INTO | D8: Q2 | E8: How to insert to a table (GSQ07) | F8: CodeChef | G8: Easy (CodeChef: easy) | H8: =HYPERLINK("https://www.codechef.com/learn/course/sql/SQ00LS01/problems/GSQ07","https://www.codechef.com/learn/course/sql/SQ00LS01/problems/GSQ07") -> https://www.codechef.com/learn/course/sql/SQ00LS01/problems/GSQ07 | I8: Yes – free (non-Pro) lesson of CodeChef 'Learn SQL'; free account to submit | J8: INSERT INTO ... VALUES (one row) | K8: CREATE TABLE | L8: Yes – one INSERT statement | M8: Added (verified) | N8: =IF(M8="Added (verified)","Yes","No") -> Yes | O8: F3 | P8: The employee table from the previous lesson is pre-loaded. Runs on SQLite.
A9: 2 | B9: SQL Basics | C9: CREATE TABLE & INSERT INTO | D9: Q3 | E9: Inserting Data into a Table (GSQ05) | F9: CodeChef | G9: Easy (CodeChef: easy) | H9: =HYPERLINK("https://www.codechef.com/learn/course/sql/SQ00LS01/problems/GSQ05","https://www.codechef.com/learn/course/sql/SQ00LS01/problems/GSQ05") -> https://www.codechef.com/learn/course/sql/SQ00LS01/problems/GSQ05 | I9: Yes – free (non-Pro) lesson of CodeChef 'Learn SQL'; free account to submit | J9: Multi-row INSERT | K9: CREATE TABLE, INSERT | L9: Yes – one INSERT with two value lists | M9: Added (verified) | N9: =IF(M9="Added (verified)","Yes","No") -> Yes | O9: G3 | P9: Runs on SQLite.
A10: 2 | B10: SQL Basics | C10: CREATE TABLE & INSERT INTO | D10: Q4 | E10: Debug this query (GSQ06) | F10: CodeChef | G10: Medium (CodeChef: easy) | H10: =HYPERLINK("https://www.codechef.com/learn/course/sql/SQ00LS01/problems/GSQ06","https://www.codechef.com/learn/course/sql/SQ00LS01/problems/GSQ06") -> https://www.codechef.com/learn/course/sql/SQ00LS01/problems/GSQ06 | I10: Yes – free (non-Pro) lesson of CodeChef 'Learn SQL'; free account to submit | J10: Fixing a broken INSERT statement | K10: T1 SELECT * | L10: Yes – corrected INSERT, then SELECT * (Topic 1) | M10: Added (verified) | N10: =IF(M10="Added (verified)","Yes","No") -> Yes | O10: H3 | P10: Runs on SQLite.
A11: 2 | B11: SQL Basics | C11: CREATE TABLE & INSERT INTO | D11: Q5 | E11: Project - Customer Database (GSQ53) | F11: CodeChef | G11: Medium (CodeChef: easy) | H11: =HYPERLINK("https://www.codechef.com/learn/course/sql/SQ00LS03/problems/GSQ53","https://www.codechef.com/learn/course/sql/SQ00LS03/problems/GSQ53") -> https://www.codechef.com/learn/course/sql/SQ00LS03/problems/GSQ53 | I11: Yes – free (non-Pro) lesson of CodeChef 'Learn SQL'; free account to submit | J11: CREATE TABLE + INSERT five rows + display the table | K11: T1 SELECT * | L11: Yes – CREATE, INSERT and SELECT * only | M11: Added (verified) | N11: =IF(M11="Added (verified)","Yes","No") -> Yes | O11: I3 | P11: Runs on SQLite.
A12: 3 | B12: SQL Basics | C12: Filtering with WHERE | D12: Q1 | E12: 1757. Recyclable and Low Fat Products | F12: LeetCode | G12: Easy (LeetCode: Easy) | H12: =HYPERLINK("https://leetcode.com/problems/recyclable-and-low-fat-products/","https://leetcode.com/problems/recyclable-and-low-fat-products/") -> https://leetcode.com/problems/recyclable-and-low-fat-products/ | I12: Yes – free problem (not Premium); free LeetCode account to submit | J12: WHERE with AND | K12: T1 SELECT | L12: Yes – WHERE low_fats = 'Y' AND recyclable = 'Y' | M12: Added (verified) | N12: =IF(M12="Added (verified)","Yes","No") -> Yes | O12: E4 | P12: Engines: MySQL, MS SQL Server, Oracle, PostgreSQL.
A13: 3 | B13: SQL Basics | C13: Filtering with WHERE | D13: Q2 | E13: Revising the Select Query I | F13: HackerRank | G13: Easy (HackerRank: Easy) | H13: =HYPERLINK("https://www.hackerrank.com/challenges/revising-the-select-query/problem","https://www.hackerrank.com/challenges/revising-the-select-query/problem") -> https://www.hackerrank.com/challenges/revising-the-select-query/problem | I13: Yes – free; free HackerRank account to submit | J13: WHERE with = and > combined by AND | K13: T1 SELECT | L13: Yes – WHERE CountryCode = 'USA' AND Population > 100000 | M13: Added (verified) | N13: =IF(M13="Added (verified)","Yes","No") -> Yes | O13: F4 | P13: Engines: MySQL, MS SQL Server, Oracle, DB2.
A14: 3 | B14: SQL Basics | C14: Filtering with WHERE | D14: Q3 | E14: High Price of Products (SQLPBP12) | F14: CodeChef | G14: Easy (CodeChef: easy) | H14: =HYPERLINK("https://www.codechef.com/practice/course/sql-case-studies-topic-wise/SQLBP01/problems/SQLPBP12","https://www.codechef.com/practice/course/sql-case-studies-topic-wise/SQLBP01/problems/SQLPBP12") -> https://www.codechef.com/practice/course/sql-case-studies-topic-wise/SQLBP01/problems/SQLPBP12 | I14: Yes – free (non-Pro) module of CodeChef 'SQL Practice Queries'; free account to submit | J14: WHERE with a > comparison | K14: T1 SELECT | L14: Yes – WHERE price > 100.00 | M14: Added (verified) | N14: =IF(M14="Added (verified)","Yes","No") -> Yes | O14: G4 | P14: Module 'Practice Basic Commands'. MySQL syntax.
A15: 3 | B15: SQL Basics | C15: Filtering with WHERE | D15: Q4 | E15: Handling NULL Values (SQLPBP07) | F15: CodeChef | G15: Easy (CodeChef: easy) | H15: =HYPERLINK("https://www.codechef.com/practice/course/sql-case-studies-topic-wise/SQLBP01/problems/SQLPBP07","https://www.codechef.com/practice/course/sql-case-studies-topic-wise/SQLBP01/problems/SQLPBP07") -> https://www.codechef.com/practice/course/sql-case-studies-topic-wise/SQLBP01/problems/SQLPBP07 | I15: Yes – free (non-Pro) module of CodeChef 'SQL Practice Queries'; free account to submit | J15: IS NULL | K15: T1 SELECT | L15: Yes – WHERE rating IS NULL | M15: Added (verified) | N15: =IF(M15="Added (verified)","Yes","No") -> Yes | O15: H4 | P15: Module 'Practice Basic Commands'. MySQL syntax.
A16: 3 | B16: SQL Basics | C16: Filtering with WHERE | D16: Q5 | E16: 584. Find Customer Referee | F16: LeetCode | G16: Medium (LeetCode: Easy) | H16: =HYPERLINK("https://leetcode.com/problems/find-customer-referee/","https://leetcode.com/problems/find-customer-referee/") -> https://leetcode.com/problems/find-customer-referee/ | I16: Yes – free problem (not Premium); free LeetCode account to submit | J16: NULL-aware filtering (<> plus OR ... IS NULL) | K16: T1 SELECT | L16: Yes – WHERE referee_id <> 2 OR referee_id IS NULL | M16: Added (verified) | N16: =IF(M16="Added (verified)","Yes","No") -> Yes | O16: I4 | P16: Engines: MySQL, MS SQL Server, Oracle, PostgreSQL.
A17: 4 | B17: SQL Basics | C17: DISTINCT, ORDER BY & LIMIT | D17: Q1 | E17: Distinct Companies (SQLPBP13) | F17: CodeChef | G17: Easy (CodeChef: easy) | H17: =HYPERLINK("https://www.codechef.com/practice/course/sql-case-studies-topic-wise/SQLBP01/problems/SQLPBP13","https://www.codechef.com/practice/course/sql-case-studies-topic-wise/SQLBP01/problems/SQLPBP13") -> https://www.codechef.com/practice/course/sql-case-studies-topic-wise/SQLBP01/problems/SQLPBP13 | I17: Yes – free (non-Pro) module of CodeChef 'SQL Practice Queries'; free account to submit | J17: SELECT DISTINCT | K17: T1 SELECT | L17: Yes – SELECT DISTINCT company_name FROM Works | M17: Added (verified) | N17: =IF(M17="Added (verified)","Yes","No") -> Yes | O17: E5 | P17: Module 'Practice Basic Commands'. MySQL syntax.
A18: 4 | B18: SQL Basics | C18: DISTINCT, ORDER BY & LIMIT | D18: Q2 | E18: Employee Names | F18: HackerRank | G18: Easy (HackerRank: Easy) | H18: =HYPERLINK("https://www.hackerrank.com/challenges/name-of-employees/problem","https://www.hackerrank.com/challenges/name-of-employees/problem") -> https://www.hackerrank.com/challenges/name-of-employees/problem | I18: Yes – free; free HackerRank account to submit | J18: ORDER BY (alphabetical) | K18: T1 SELECT | L18: Yes – SELECT name FROM Employee ORDER BY name | M18: Added (verified) | N18: =IF(M18="Added (verified)","Yes","No") -> Yes | O18: F5 | P18: Engines: MySQL, MS SQL Server, Oracle, DB2.
A19: 4 | B19: SQL Basics | C19: DISTINCT, ORDER BY & LIMIT | D19: Q3 | E19: 1148. Article Views I | F19: LeetCode | G19: Easy (LeetCode: Easy) | H19: =HYPERLINK("https://leetcode.com/problems/article-views-i/","https://leetcode.com/problems/article-views-i/") -> https://leetcode.com/problems/article-views-i/ | I19: Yes – free problem (not Premium); free LeetCode account to submit | J19: DISTINCT + ORDER BY after a WHERE filter | K19: T1, T3 WHERE | L19: Yes – SELECT DISTINCT author_id ... WHERE author_id = viewer_id ORDER BY id | M19: Added (verified) | N19: =IF(M19="Added (verified)","Yes","No") -> Yes | O19: G5 | P19: Engines: MySQL, MS SQL Server, Oracle, PostgreSQL.
A20: 4 | B20: SQL Basics | C20: DISTINCT, ORDER BY & LIMIT | D20: Q4 | E20: Employee Salaries | F20: HackerRank | G20: Medium (HackerRank: Easy) | H20: =HYPERLINK("https://www.hackerrank.com/challenges/salary-of-employees/problem","https://www.hackerrank.com/challenges/salary-of-employees/problem") -> https://www.hackerrank.com/challenges/salary-of-employees/problem | I20: Yes – free; free HackerRank account to submit | J20: Filter, then sort by a key | K20: T3 WHERE | L20: Yes – WHERE salary > 2000 AND months < 10 ORDER BY employee_id | M20: Added (verified) | N20: =IF(M20="Added (verified)","Yes","No") -> Yes | O20: H5 | P20: Engines: MySQL, MS SQL Server, Oracle, DB2.
A21: 4 | B21: SQL Basics | C21: DISTINCT, ORDER BY & LIMIT | D21: Q5 | E21: Task-3C Data Retrieval Using Queries (RSMSPR03C) | F21: CodeChef | G21: Medium (CodeChef: easy) | H21: =HYPERLINK("https://www.codechef.com/learn/course/sql/BEGSQLPR/problems/RSMSPR03C","https://www.codechef.com/learn/course/sql/BEGSQLPR/problems/RSMSPR03C") -> https://www.codechef.com/learn/course/sql/BEGSQLPR/problems/RSMSPR03C | I21: Yes – free (non-Pro) lesson of CodeChef 'Learn SQL'; free account to submit | J21: Top-N with ORDER BY ... DESC LIMIT | K21: T1 SELECT | L21: Yes – ORDER BY price DESC LIMIT 2 | M21: Added (verified) | N21: =IF(M21="Added (verified)","Yes","No") -> Yes | O21: I5 | P21: Lesson of the free 'Retail store management system' project; the tables it needs are pre-loaded and shown in the statement. Runs on SQLite.
A22: 5 | B22: SQL Basics | C22: BETWEEN, IN & LIKE | D22: Q1 | E22: BETWEEN (GSQ19A) | F22: CodeChef | G22: Easy (CodeChef: easy) | H22: =HYPERLINK("https://www.codechef.com/learn/course/sql/SQ00LS04/problems/GSQ19A","https://www.codechef.com/learn/course/sql/SQ00LS04/problems/GSQ19A") -> https://www.codechef.com/learn/course/sql/SQ00LS04/problems/GSQ19A | I22: Yes – free (non-Pro) lesson of CodeChef 'Learn SQL'; free account to submit | J22: BETWEEN ... AND ... | K22: T1, T3 WHERE | L22: Yes – WHERE passenger_name BETWEEN 'A' AND 'D' | M22: Added (verified) | N22: =IF(M22="Added (verified)","Yes","No") -> Yes | O22: E6 | P22: Runs on SQLite.
A23: 5 | B23: SQL Basics | C23: BETWEEN, IN & LIKE | D23: Q2 | E23: Practice - Filter with multiple Like patterns (GSQ26) | F23: CodeChef | G23: Easy (CodeChef: easy) | H23: =HYPERLINK("https://www.codechef.com/learn/course/sql/SQ00LS05/problems/GSQ26","https://www.codechef.com/learn/course/sql/SQ00LS05/problems/GSQ26") -> https://www.codechef.com/learn/course/sql/SQ00LS05/problems/GSQ26 | I23: Yes – free (non-Pro) lesson of CodeChef 'Learn SQL'; free account to submit | J23: LIKE with % wildcards combined by AND | K23: T3 WHERE / AND | L23: Yes – destination LIKE '%o' AND origin LIKE 'M%' | M23: Added (verified) | N23: =IF(M23="Added (verified)","Yes","No") -> Yes | O23: F6 | P23: Runs on SQLite.
A24: 5 | B24: SQL Basics | C24: BETWEEN, IN & LIKE | D24: Q3 | E24: 1527. Patients With a Condition | F24: LeetCode | G24: Medium (LeetCode: Easy) | H24: =HYPERLINK("https://leetcode.com/problems/patients-with-a-condition/","https://leetcode.com/problems/patients-with-a-condition/") -> https://leetcode.com/problems/patients-with-a-condition/ | I24: Yes – free problem (not Premium); free LeetCode account to submit | J24: LIKE on a word inside a space-separated list | K24: T3 OR | L24: Yes – conditions LIKE 'DIAB1%' OR conditions LIKE '% DIAB1%' | M24: Added (verified) | N24: =IF(M24="Added (verified)","Yes","No") -> Yes | O24: G6 | P24: Engines: MySQL, MS SQL Server, Oracle, PostgreSQL.
A25: 5 | B25: SQL Basics | C25: BETWEEN, IN & LIKE | D25: Q4 | E25: Weather Observation Station 6 | F25: HackerRank | G25: Medium (HackerRank: Easy) | H25: =HYPERLINK("https://www.hackerrank.com/challenges/weather-observation-station-6/problem","https://www.hackerrank.com/challenges/weather-observation-station-6/problem") -> https://www.hackerrank.com/challenges/weather-observation-station-6/problem | I25: Yes – free; free HackerRank account to submit | J25: LIKE patterns for a first letter + DISTINCT | K25: T3 OR, T4 DISTINCT | L25: Yes – five OR'ed LIKE patterns ('a%', 'e%', ...) with DISTINCT (Topic 4) | M25: Added (verified) | N25: =IF(M25="Added (verified)","Yes","No") -> Yes | O25: H6 | P25: Engines: MySQL, MS SQL Server, Oracle, DB2.
A26: 5 | B26: SQL Basics | C26: BETWEEN, IN & LIKE | D26: Q5 | E26: Weather Observation Station 12 | F26: HackerRank | G26: Challenging (HackerRank: Easy) | H26: =HYPERLINK("https://www.hackerrank.com/challenges/weather-observation-station-12/problem","https://www.hackerrank.com/challenges/weather-observation-station-12/problem") -> https://www.hackerrank.com/challenges/weather-observation-station-12/problem | I26: Yes – free; free HackerRank account to submit | J26: NOT LIKE on first and last letters + DISTINCT | K26: T3 AND, T4 DISTINCT | L26: Yes – NOT LIKE patterns for both ends with DISTINCT (Topic 4) | M26: Added (verified) | N26: =IF(M26="Added (verified)","Yes","No") -> Yes | O26: I6 | P26: Engines: MySQL, MS SQL Server, Oracle, DB2.
A27: 6 | B27: Functions & Aggregation | C27: String Functions | D27: Q1 | E27: 1683. Invalid Tweets | F27: LeetCode | G27: Easy (LeetCode: Easy) | H27: =HYPERLINK("https://leetcode.com/problems/invalid-tweets/","https://leetcode.com/problems/invalid-tweets/") -> https://leetcode.com/problems/invalid-tweets/ | I27: Yes – free problem (not Premium); free LeetCode account to submit | J27: LENGTH() / CHAR_LENGTH() | K27: T3 WHERE | L27: Yes – WHERE CHAR_LENGTH(content) > 15 | M27: Added (verified) | N27: =IF(M27="Added (verified)","Yes","No") -> Yes | O27: E7 | P27: Engines: MySQL, MS SQL Server, Oracle, PostgreSQL.
A28: 6 | B28: Functions & Aggregation | C28: String Functions | D28: Q2 | E28: Higher Than 75 Marks | F28: HackerRank | G28: Easy (HackerRank: Easy) | H28: =HYPERLINK("https://www.hackerrank.com/challenges/more-than-75-marks/problem","https://www.hackerrank.com/challenges/more-than-75-marks/problem") -> https://www.hackerrank.com/challenges/more-than-75-marks/problem | I28: Yes – free; free HackerRank account to submit | J28: RIGHT() / SUBSTRING() as a sort key | K28: T3 WHERE, T4 ORDER BY | L28: Yes – WHERE Marks > 75 ORDER BY RIGHT(Name, 3), ID | M28: Added (verified) | N28: =IF(M28="Added (verified)","Yes","No") -> Yes | O28: F7 | P28: Engines: MySQL, MS SQL Server, Oracle, DB2.
A29: 6 | B29: Functions & Aggregation | C29: String Functions | D29: Q3 | E29: 1667. Fix Names in a Table | F29: LeetCode | G29: Medium (LeetCode: Easy) | H29: =HYPERLINK("https://leetcode.com/problems/fix-names-in-a-table/","https://leetcode.com/problems/fix-names-in-a-table/") -> https://leetcode.com/problems/fix-names-in-a-table/ | I29: Yes – free problem (not Premium); free LeetCode account to submit | J29: UPPER, LOWER, SUBSTRING and CONCAT together | K29: T4 ORDER BY | L29: Yes – CONCAT(UPPER(LEFT(name,1)), LOWER(SUBSTRING(name,2))) ... ORDER BY user_id | M29: Added (verified) | N29: =IF(M29="Added (verified)","Yes","No") -> Yes | O29: G7 | P29: Engines: MySQL, MS SQL Server, Oracle, PostgreSQL.
A30: 6 | B30: Functions & Aggregation | C30: String Functions | D30: Q4 | E30: Weather Observation Station 5 | F30: HackerRank | G30: Medium (HackerRank: Easy) | H30: =HYPERLINK("https://www.hackerrank.com/challenges/weather-observation-station-5/problem","https://www.hackerrank.com/challenges/weather-observation-station-5/problem") -> https://www.hackerrank.com/challenges/weather-observation-station-5/problem | I30: Yes – free; free HackerRank account to submit | J30: LENGTH() as a sort key with LIMIT 1 | K30: T4 ORDER BY / LIMIT | L30: Yes – two separate SELECTs, each ORDER BY LENGTH(CITY), CITY LIMIT 1 (UNION not needed) | M30: Added (verified) | N30: =IF(M30="Added (verified)","Yes","No") -> Yes | O30: H7 | P30: Engines: MySQL, MS SQL Server, Oracle, DB2.
A31: 6 | B31: Functions & Aggregation | C31: String Functions | D31: Q5 | E31: 1517. Find Users With Valid E-Mails | F31: LeetCode | G31: Challenging (LeetCode: Easy) | H31: =HYPERLINK("https://leetcode.com/problems/find-users-with-valid-e-mails/","https://leetcode.com/problems/find-users-with-valid-e-mails/") -> https://leetcode.com/problems/find-users-with-valid-e-mails/ | I31: Yes – free problem (not Premium); free LeetCode account to submit | J31: Regular-expression matching (REGEXP / REGEXP_LIKE) | K31: T3 WHERE, T5 LIKE | L31: Yes – one REGEXP condition in WHERE | M31: Added (verified) | N31: =IF(M31="Added (verified)","Yes","No") -> Yes | O31: I7 | P31: Engines: MySQL, MS SQL Server, Oracle, PostgreSQL.
A32: 7 | B32: Functions & Aggregation | C32: Aggregate Functions | D32: Q1 | E32: Revising Aggregations - The Count Function | F32: HackerRank | G32: Easy (HackerRank: Easy) | H32: =HYPERLINK("https://www.hackerrank.com/challenges/revising-aggregations-the-count-function/problem","https://www.hackerrank.com/challenges/revising-aggregations-the-count-function/problem") -> https://www.hackerrank.com/challenges/revising-aggregations-the-count-function/problem | I32: Yes – free; free HackerRank account to submit | J32: COUNT() with WHERE | K32: T3 WHERE | L32: Yes – SELECT COUNT(*) ... WHERE Population > 100000 | M32: Added (verified) | N32: =IF(M32="Added (verified)","Yes","No") -> Yes | O32: E8 | P32: Engines: MySQL, MS SQL Server, Oracle, DB2.
A33: 7 | B33: Functions & Aggregation | C33: Aggregate Functions | D33: Q2 | E33: Fiction Collection Size (SQLPBP02) | F33: CodeChef | G33: Easy (CodeChef: easy) | H33: =HYPERLINK("https://www.codechef.com/practice/course/sql-case-studies-topic-wise/SQLBP01/problems/SQLPBP02","https://www.codechef.com/practice/course/sql-case-studies-topic-wise/SQLBP01/problems/SQLPBP02") -> https://www.codechef.com/practice/course/sql-case-studies-topic-wise/SQLBP01/problems/SQLPBP02 | I33: Yes – free (non-Pro) module of CodeChef 'SQL Practice Queries'; free account to submit | J33: COUNT() with WHERE and an alias | K33: T1 AS, T3 WHERE | L33: Yes – COUNT(*) AS fiction_count ... WHERE genre = 'Fiction' | M33: Added (verified) | N33: =IF(M33="Added (verified)","Yes","No") -> Yes | O33: F8 | P33: Module 'Practice Basic Commands'. MySQL syntax.
A34: 7 | B34: Functions & Aggregation | C34: Aggregate Functions | D34: Q3 | E34: Average Salary (SQLPBP14) | F34: CodeChef | G34: Easy (CodeChef: easy) | H34: =HYPERLINK("https://www.codechef.com/practice/course/sql-case-studies-topic-wise/SQLBP01/problems/SQLPBP14","https://www.codechef.com/practice/course/sql-case-studies-topic-wise/SQLBP01/problems/SQLPBP14") -> https://www.codechef.com/practice/course/sql-case-studies-topic-wise/SQLBP01/problems/SQLPBP14 | I34: Yes – free (non-Pro) module of CodeChef 'SQL Practice Queries'; free account to submit | J34: AVG() over the whole table | K34: T1 AS | L34: Yes – SELECT AVG(salary) AS avg_salary FROM Works | M34: Added (verified) | N34: =IF(M34="Added (verified)","Yes","No") -> Yes | O34: G8 | P34: Module 'Practice Basic Commands'. MySQL syntax.
A35: 7 | B35: Functions & Aggregation | C35: Aggregate Functions | D35: Q4 | E35: Problem - SUM() and AVG() (GSQ44) | F35: CodeChef | G35: Medium (CodeChef: easy) | H35: =HYPERLINK("https://www.codechef.com/learn/course/sql/SQ00LS09/problems/GSQ44","https://www.codechef.com/learn/course/sql/SQ00LS09/problems/GSQ44") -> https://www.codechef.com/learn/course/sql/SQ00LS09/problems/GSQ44 | I35: Yes – free (non-Pro) lesson of CodeChef 'Learn SQL'; free account to submit | J35: SUM() and AVG() with WHERE | K35: T1 AS, T3 WHERE | L35: Yes – two SELECTs using SUM / AVG with WHERE | M35: Added (verified) | N35: =IF(M35="Added (verified)","Yes","No") -> Yes | O35: H8 | P35: Runs on SQLite.
A36: 7 | B36: Functions & Aggregation | C36: Aggregate Functions | D36: Q5 | E36: Population Density Difference | F36: HackerRank | G36: Medium (HackerRank: Easy) | H36: =HYPERLINK("https://www.hackerrank.com/challenges/population-density-difference/problem","https://www.hackerrank.com/challenges/population-density-difference/problem") -> https://www.hackerrank.com/challenges/population-density-difference/problem | I36: Yes – free; free HackerRank account to submit | J36: Arithmetic on two aggregates (MAX − MIN) | K36: T1 SELECT | L36: Yes – SELECT MAX(Population) - MIN(Population) | M36: Added (verified) | N36: =IF(M36="Added (verified)","Yes","No") -> Yes | O36: I8 | P36: Engines: MySQL, MS SQL Server, Oracle, DB2.
A37: 8 | B37: Functions & Aggregation | C37: Numeric Functions | D37: Q1 | E37: Weather Observation Station 3 | F37: HackerRank | G37: Easy (HackerRank: Easy) | H37: =HYPERLINK("https://www.hackerrank.com/challenges/weather-observation-station-3/problem","https://www.hackerrank.com/challenges/weather-observation-station-3/problem") -> https://www.hackerrank.com/challenges/weather-observation-station-3/problem | I37: Yes – free; free HackerRank account to submit | J37: MOD() / % to test even numbers | K37: T3 WHERE, T4 DISTINCT | L37: Yes – SELECT DISTINCT CITY ... WHERE MOD(ID, 2) = 0 | M37: Added (verified) | N37: =IF(M37="Added (verified)","Yes","No") -> Yes | O37: E9 | P37: Engines: MySQL, MS SQL Server, Oracle, DB2.
A38: 8 | B38: Functions & Aggregation | C38: Numeric Functions | D38: Q2 | E38: 620. Not Boring Movies | F38: LeetCode | G38: Easy (LeetCode: Easy) | H38: =HYPERLINK("https://leetcode.com/problems/not-boring-movies/","https://leetcode.com/problems/not-boring-movies/") -> https://leetcode.com/problems/not-boring-movies/ | I38: Yes – free problem (not Premium); free LeetCode account to submit | J38: MOD() for odd ids + sorting | K38: T3 WHERE, T4 ORDER BY | L38: Yes – WHERE MOD(id, 2) = 1 AND description <> 'boring' ORDER BY rating DESC | M38: Added (verified) | N38: =IF(M38="Added (verified)","Yes","No") -> Yes | O38: F9 | P38: Engines: MySQL, MS SQL Server, Oracle, PostgreSQL.
A39: 8 | B39: Functions & Aggregation | C39: Numeric Functions | D39: Q3 | E39: Problem-ROUND() (GSQ41) | F39: CodeChef | G39: Easy (CodeChef: easy) | H39: =HYPERLINK("https://www.codechef.com/learn/course/sql/SQ00LS08/problems/GSQ41","https://www.codechef.com/learn/course/sql/SQ00LS08/problems/GSQ41") -> https://www.codechef.com/learn/course/sql/SQ00LS08/problems/GSQ41 | I39: Yes – free (non-Pro) lesson of CodeChef 'Learn SQL'; free account to submit | J39: ROUND() to 2 decimal places | K39: T1 AS | L39: Yes – SELECT ROUND(Payout, 2) AS payout | M39: Added (verified) | N39: =IF(M39="Added (verified)","Yes","No") -> Yes | O39: G9 | P39: Runs on SQLite.
A40: 8 | B40: Functions & Aggregation | C40: Numeric Functions | D40: Q4 | E40: The Blunder | F40: HackerRank | G40: Medium (HackerRank: Easy) | H40: =HYPERLINK("https://www.hackerrank.com/challenges/the-blunder/problem","https://www.hackerrank.com/challenges/the-blunder/problem") -> https://www.hackerrank.com/challenges/the-blunder/problem | I40: Yes – free; free HackerRank account to submit | J40: CEIL() of a difference of averages | K40: T6 REPLACE, T7 AVG | L40: Yes – CEIL(AVG(Salary) - AVG(REPLACE(Salary, '0', ''))) | M40: Added (verified) | N40: =IF(M40="Added (verified)","Yes","No") -> Yes | O40: H9 | P40: Engines: MySQL, MS SQL Server, Oracle, DB2.
A41: 8 | B41: Functions & Aggregation | C41: Numeric Functions | D41: Q5 | E41: Weather Observation Station 19 | F41: HackerRank | G41: Challenging (HackerRank: Medium) | H41: =HYPERLINK("https://www.hackerrank.com/challenges/weather-observation-station-19/problem","https://www.hackerrank.com/challenges/weather-observation-station-19/problem") -> https://www.hackerrank.com/challenges/weather-observation-station-19/problem | I41: Yes – free; free HackerRank account to submit | J41: SQRT / POWER (Euclidean distance) + ROUND | K41: T7 MIN / MAX | L41: Yes – ROUND(SQRT(POWER(MAX-MIN, 2) + POWER(MAX-MIN, 2)), 4) | M41: Added (verified) | N41: =IF(M41="Added (verified)","Yes","No") -> Yes | O41: I9 | P41: Engines: MySQL, MS SQL Server, Oracle, DB2.
A42: 9 | B42: Functions & Aggregation | C42: GROUP BY | D42: Q1 | E42: 2356. Number of Unique Subjects Taught by Each Teacher | F42: LeetCode | G42: Easy (LeetCode: Easy) | H42: =HYPERLINK("https://leetcode.com/problems/number-of-unique-subjects-taught-by-each-teacher/","https://leetcode.com/problems/number-of-unique-subjects-taught-by-each-teacher/") -> https://leetcode.com/problems/number-of-unique-subjects-taught-by-each-teacher/ | I42: Yes – free problem (not Premium); free LeetCode account to submit | J42: GROUP BY with COUNT(DISTINCT) | K42: T4 DISTINCT, T7 COUNT | L42: Yes – COUNT(DISTINCT subject_id) ... GROUP BY teacher_id | M42: Added (verified) | N42: =IF(M42="Added (verified)","Yes","No") -> Yes | O42: E10 | P42: Engines: MySQL, MS SQL Server, Oracle, PostgreSQL.
A43: 9 | B43: Functions & Aggregation | C43: GROUP BY | D43: Q2 | E43: Department of Each Employee (SQLPBP09) | F43: CodeChef | G43: Easy (CodeChef: easy) | H43: =HYPERLINK("https://www.codechef.com/practice/course/sql-case-studies-topic-wise/SQLBP01/problems/SQLPBP09","https://www.codechef.com/practice/course/sql-case-studies-topic-wise/SQLBP01/problems/SQLPBP09") -> https://www.codechef.com/practice/course/sql-case-studies-topic-wise/SQLBP01/problems/SQLPBP09 | I43: Yes – free (non-Pro) module of CodeChef 'SQL Practice Queries'; free account to submit | J43: GROUP BY with COUNT | K43: T1 AS, T7 COUNT | L43: Yes – SELECT department, COUNT(*) AS total_employees ... GROUP BY department | M43: Added (verified) | N43: =IF(M43="Added (verified)","Yes","No") -> Yes | O43: F10 | P43: Module 'Practice Basic Commands'. MySQL syntax.
A44: 9 | B44: Functions & Aggregation | C44: GROUP BY | D44: Q3 | E44: 1741. Find Total Time Spent by Each Employee | F44: LeetCode | G44: Easy (LeetCode: Easy) | H44: =HYPERLINK("https://leetcode.com/problems/find-total-time-spent-by-each-employee/","https://leetcode.com/problems/find-total-time-spent-by-each-employee/") -> https://leetcode.com/problems/find-total-time-spent-by-each-employee/ | I44: Yes – free problem (not Premium); free LeetCode account to submit | J44: GROUP BY two columns with SUM of an expression | K44: T1 AS, T7 SUM | L44: Yes – SUM(out_time - in_time) ... GROUP BY event_day, emp_id | M44: Added (verified) | N44: =IF(M44="Added (verified)","Yes","No") -> Yes | O44: G10 | P44: Engines: MySQL, MS SQL Server, Oracle, PostgreSQL.
A45: 9 | B45: Functions & Aggregation | C45: GROUP BY | D45: Q4 | E45: 1484. Group Sold Products By The Date | F45: LeetCode | G45: Medium (LeetCode: Easy) | H45: =HYPERLINK("https://leetcode.com/problems/group-sold-products-by-the-date/","https://leetcode.com/problems/group-sold-products-by-the-date/") -> https://leetcode.com/problems/group-sold-products-by-the-date/ | I45: Yes – free problem (not Premium); free LeetCode account to submit | J45: GROUP BY with COUNT(DISTINCT) and GROUP_CONCAT / STRING_AGG | K45: T4 DISTINCT / ORDER BY, T7 | L45: Yes – COUNT(DISTINCT product), GROUP_CONCAT(DISTINCT product ORDER BY product) ... GROUP BY sell_date | M45: Added (verified) | N45: =IF(M45="Added (verified)","Yes","No") -> Yes | O45: H10 | P45: Engines: MySQL, MS SQL Server, Oracle, PostgreSQL.
A46: 9 | B46: Functions & Aggregation | C46: GROUP BY | D46: Q5 | E46: The PADS | F46: HackerRank | G46: Challenging (HackerRank: Medium) | H46: =HYPERLINK("https://www.hackerrank.com/challenges/the-pads/problem","https://www.hackerrank.com/challenges/the-pads/problem") -> https://www.hackerrank.com/challenges/the-pads/problem | I46: Yes – free; free HackerRank account to submit | J46: GROUP BY + COUNT combined with string building | K46: T4 ORDER BY, T6 CONCAT / LEFT / LOWER, T7 COUNT | L46: Yes – two SELECTs: CONCAT(...) ORDER BY Name; COUNT(*) ... GROUP BY Occupation ORDER BY the count | M46: Added (verified) | N46: =IF(M46="Added (verified)","Yes","No") -> Yes | O46: I10 | P46: Engines: MySQL, MS SQL Server, Oracle, DB2.
A47: 10 | B47: Functions & Aggregation | C47: HAVING | D47: Q1 | E47: 182. Duplicate Emails | F47: LeetCode | G47: Easy (LeetCode: Easy) | H47: =HYPERLINK("https://leetcode.com/problems/duplicate-emails/","https://leetcode.com/problems/duplicate-emails/") -> https://leetcode.com/problems/duplicate-emails/ | I47: Yes – free problem (not Premium); free LeetCode account to submit | J47: GROUP BY ... HAVING COUNT(*) > 1 | K47: T9 GROUP BY | L47: Yes – GROUP BY email HAVING COUNT(*) > 1 | M47: Added (verified) | N47: =IF(M47="Added (verified)","Yes","No") -> Yes | O47: E11 | P47: Engines: MySQL, MS SQL Server, Oracle, PostgreSQL.
A48: 10 | B48: Functions & Aggregation | C48: HAVING | D48: Q2 | E48: 596. Classes With at Least 5 Students | F48: LeetCode | G48: Easy (LeetCode: Easy) | H48: =HYPERLINK("https://leetcode.com/problems/classes-with-at-least-5-students/","https://leetcode.com/problems/classes-with-at-least-5-students/") -> https://leetcode.com/problems/classes-with-at-least-5-students/ | I48: Yes – free problem (not Premium); free LeetCode account to submit | J48: HAVING with a count threshold | K48: T9 GROUP BY | L48: Yes – GROUP BY class HAVING COUNT(student) >= 5 | M48: Added (verified) | N48: =IF(M48="Added (verified)","Yes","No") -> Yes | O48: F11 | P48: Engines: MySQL, MS SQL Server, Oracle, PostgreSQL.
A49: 10 | B49: Functions & Aggregation | C49: HAVING | D49: Q3 | E49: Having (GSQ46) | F49: CodeChef | G49: Medium (CodeChef: medium) | H49: =HYPERLINK("https://www.codechef.com/learn/course/sql/SQ00LS09/problems/GSQ46","https://www.codechef.com/learn/course/sql/SQ00LS09/problems/GSQ46") -> https://www.codechef.com/learn/course/sql/SQ00LS09/problems/GSQ46 | I49: Yes – free (non-Pro) lesson of CodeChef 'Learn SQL'; free account to submit | J49: HAVING on COUNT while selecting AVG | K49: T7 AVG, T9 GROUP BY | L49: Yes – AVG(Payout) ... GROUP BY Department HAVING COUNT(*) > 3 | M49: Added (verified) | N49: =IF(M49="Added (verified)","Yes","No") -> Yes | O49: G11 | P49: Runs on SQLite.
A50: 10 | B50: Functions & Aggregation | C50: HAVING | D50: Q4 | E50: 1050. Actors and Directors Who Cooperated At Least Three Times | F50: LeetCode | G50: Medium (LeetCode: Easy) | H50: =HYPERLINK("https://leetcode.com/problems/actors-and-directors-who-cooperated-at-least-three-times/","https://leetcode.com/problems/actors-and-directors-who-cooperated-at-least-three-times/") -> https://leetcode.com/problems/actors-and-directors-who-cooperated-at-least-three-times/ | I50: Yes – free problem (not Premium); free LeetCode account to submit | J50: HAVING on a two-column group | K50: T9 GROUP BY | L50: Yes – GROUP BY actor_id, director_id HAVING COUNT(*) >= 3 | M50: Added (verified) | N50: =IF(M50="Added (verified)","Yes","No") -> Yes | O50: H11 | P50: Engines: MySQL, MS SQL Server, Oracle, PostgreSQL.
A51: 10 | B51: Functions & Aggregation | C51: HAVING | D51: Q5 | E51: Problem-Group By & Having (GSQ47) | F51: CodeChef | G51: Challenging (CodeChef: medium) | H51: =HYPERLINK("https://www.codechef.com/learn/course/sql/SQ00LS09/problems/GSQ47","https://www.codechef.com/learn/course/sql/SQ00LS09/problems/GSQ47") -> https://www.codechef.com/learn/course/sql/SQ00LS09/problems/GSQ47 | I51: Yes – free (non-Pro) lesson of CodeChef 'Learn SQL'; free account to submit | J51: HAVING on SUM while selecting AVG | K51: T7 SUM / AVG, T9 GROUP BY | L51: Yes – AVG(Payout) ... GROUP BY Department HAVING SUM(Payout) > 40 | M51: Added (verified) | N51: =IF(M51="Added (verified)","Yes","No") -> Yes | O51: I11 | P51: Runs on SQLite.
A52: 11 | B52: Conditional Logic & Dates | C52: CASE Expressions | D52: Q1 | E52: Type of Triangle | F52: HackerRank | G52: Easy (HackerRank: Easy) | H52: =HYPERLINK("https://www.hackerrank.com/challenges/what-type-of-triangle/problem","https://www.hackerrank.com/challenges/what-type-of-triangle/problem") -> https://www.hackerrank.com/challenges/what-type-of-triangle/problem | I52: Yes – free; free HackerRank account to submit | J52: Searched CASE with ordered conditions | K52: T3 comparisons | L52: Yes – CASE WHEN A + B <= C ... THEN 'Not A Triangle' WHEN ... END | M52: Added (verified) | N52: =IF(M52="Added (verified)","Yes","No") -> Yes | O52: E12 | P52: Engines: MySQL, MS SQL Server, Oracle, DB2.
A53: 11 | B53: Conditional Logic & Dates | C53: CASE Expressions | D53: Q2 | E53: 610. Triangle Judgement | F53: LeetCode | G53: Easy (LeetCode: Easy) | H53: =HYPERLINK("https://leetcode.com/problems/triangle-judgement/","https://leetcode.com/problems/triangle-judgement/") -> https://leetcode.com/problems/triangle-judgement/ | I53: Yes – free problem (not Premium); free LeetCode account to submit | J53: CASE returning 'Yes' / 'No' | K53: T3 comparisons | L53: Yes – CASE WHEN x + y > z AND ... THEN 'Yes' ELSE 'No' END | M53: Added (verified) | N53: =IF(M53="Added (verified)","Yes","No") -> Yes | O53: F12 | P53: Engines: MySQL, MS SQL Server, Oracle, PostgreSQL.
A54: 11 | B54: Conditional Logic & Dates | C54: CASE Expressions | D54: Q3 | E54: 1873. Calculate Special Bonus | F54: LeetCode | G54: Medium (LeetCode: Easy) | H54: =HYPERLINK("https://leetcode.com/problems/calculate-special-bonus/","https://leetcode.com/problems/calculate-special-bonus/") -> https://leetcode.com/problems/calculate-special-bonus/ | I54: Yes – free problem (not Premium); free LeetCode account to submit | J54: CASE combining MOD and NOT LIKE | K54: T4 ORDER BY, T5 LIKE, T8 MOD | L54: Yes – CASE WHEN MOD(employee_id, 2) = 1 AND name NOT LIKE 'M%' THEN salary ELSE 0 END | M54: Added (verified) | N54: =IF(M54="Added (verified)","Yes","No") -> Yes | O54: G12 | P54: Engines: MySQL, MS SQL Server, Oracle, PostgreSQL.
A55: 11 | B55: Conditional Logic & Dates | C55: CASE Expressions | D55: Q4 | E55: Case - When (GSQ81) | F55: CodeChef | G55: Medium (CodeChef: medium) | H55: =HYPERLINK("https://www.codechef.com/learn/course/sql-intermediate/SQ00BS08/problems/GSQ81","https://www.codechef.com/learn/course/sql-intermediate/SQ00BS08/problems/GSQ81") -> https://www.codechef.com/learn/course/sql-intermediate/SQ00BS08/problems/GSQ81 | I55: Yes – free (non-Pro) lesson of CodeChef 'Learn Advanced SQL'; free account to submit | J55: CASE to bucket rows, then COUNT per bucket | K55: T7 COUNT, T9 GROUP BY | L55: Yes – CASE grade buckets with COUNT(*) ... GROUP BY 1 | M55: Added (verified) | N55: =IF(M55="Added (verified)","Yes","No") -> Yes | O55: H12 | P55: Runs on SQLite.
A56: 11 | B56: Conditional Logic & Dates | C56: CASE Expressions | D56: Q5 | E56: Sum using Case (GSQ83) | F56: CodeChef | G56: Medium (CodeChef: easy) | H56: =HYPERLINK("https://www.codechef.com/learn/course/sql-intermediate/SQ00BS08/problems/GSQ83","https://www.codechef.com/learn/course/sql-intermediate/SQ00BS08/problems/GSQ83") -> https://www.codechef.com/learn/course/sql-intermediate/SQ00BS08/problems/GSQ83 | I56: Yes – free (non-Pro) lesson of CodeChef 'Learn Advanced SQL'; free account to submit | J56: CASE inside SUM (conditional sum per group) | K56: T7 SUM, T9 GROUP BY | L56: Yes – SUM(CASE WHEN Age > 20 THEN Fee ELSE 0 END) ... GROUP BY Department | M56: Added (verified) | N56: =IF(M56="Added (verified)","Yes","No") -> Yes | O56: I12 | P56: Runs on SQLite.
A57: 12 | B57: Conditional Logic & Dates | C57: Date & Time Functions | D57: Q1 | E57: 1141. User Activity for the Past 30 Days I | F57: LeetCode | G57: Easy (LeetCode: Easy) | H57: =HYPERLINK("https://leetcode.com/problems/user-activity-for-the-past-30-days-i/","https://leetcode.com/problems/user-activity-for-the-past-30-days-i/") -> https://leetcode.com/problems/user-activity-for-the-past-30-days-i/ | I57: Yes – free problem (not Premium); free LeetCode account to submit | J57: Date-range filter (DATEDIFF / DATE_SUB or BETWEEN dates) | K57: T5 BETWEEN, T9 GROUP BY with COUNT(DISTINCT) | L57: Yes – 30-day window ending 2019-07-27, COUNT(DISTINCT user_id) per day | M57: Added (verified) | N57: =IF(M57="Added (verified)","Yes","No") -> Yes | O57: E13 | P57: Engines: MySQL, MS SQL Server, Oracle, PostgreSQL.
A58: 12 | B58: Conditional Logic & Dates | C58: Date & Time Functions | D58: Q2 | E58: 1890. The Latest Login in 2020 | F58: LeetCode | G58: Easy (LeetCode: Easy) | H58: =HYPERLINK("https://leetcode.com/problems/the-latest-login-in-2020/","https://leetcode.com/problems/the-latest-login-in-2020/") -> https://leetcode.com/problems/the-latest-login-in-2020/ | I58: Yes – free problem (not Premium); free LeetCode account to submit | J58: YEAR() extraction + MAX per group | K58: T7 MAX, T9 GROUP BY | L58: Yes – WHERE YEAR(time_stamp) = 2020 ... MAX(time_stamp) GROUP BY user_id | M58: Added (verified) | N58: =IF(M58="Added (verified)","Yes","No") -> Yes | O58: F13 | P58: Engines: MySQL, MS SQL Server, Oracle, PostgreSQL.
A59: 12 | B59: Conditional Logic & Dates | C59: Date & Time Functions | D59: Q3 | E59: Task-6C Aggregations & Grouping (RSMSPR06C) | F59: CodeChef | G59: Medium (CodeChef: medium) | H59: =HYPERLINK("https://www.codechef.com/learn/course/sql/BEGSQLPR/problems/RSMSPR06C","https://www.codechef.com/learn/course/sql/BEGSQLPR/problems/RSMSPR06C") -> https://www.codechef.com/learn/course/sql/BEGSQLPR/problems/RSMSPR06C | I59: Yes – free (non-Pro) lesson of CodeChef 'Learn SQL'; free account to submit | J59: Grouping by month with strftime('%Y-%m', ...) | K59: T7 COUNT, T9 GROUP BY | L59: Yes – month key from strftime, COUNT(*) ... GROUP BY month | M59: Added (verified) | N59: =IF(M59="Added (verified)","Yes","No") -> Yes | O59: G13 | P59: Lesson of the free 'Retail store management system' project; the tables it needs are pre-loaded and shown in the statement. The statement gives the strftime pattern. Runs on SQLite.
A60: 12 | B60: Conditional Logic & Dates | C60: Date & Time Functions | D60: Q4 | E60: Task-8 Date Functions (RSMSPR08) | F60: CodeChef | G60: Medium (CodeChef: medium) | H60: =HYPERLINK("https://www.codechef.com/learn/course/sql/BEGSQLPR/problems/RSMSPR08","https://www.codechef.com/learn/course/sql/BEGSQLPR/problems/RSMSPR08") -> https://www.codechef.com/learn/course/sql/BEGSQLPR/problems/RSMSPR08 | I60: Yes – free (non-Pro) lesson of CodeChef 'Learn SQL'; free account to submit | J60: Month filters, latest date, JULIANDAY differences, DATE() ranges | K60: T5 BETWEEN, T7 MIN / MAX, T9 GROUP BY | L60: Yes – five short date queries using only date functions, aggregates and GROUP BY | M60: Added (verified) | N60: =IF(M60="Added (verified)","Yes","No") -> Yes | O60: H13 | P60: Lesson of the free 'Retail store management system' project; the tables it needs are pre-loaded and shown in the statement. Runs on SQLite.
A61: 12 | B61: Conditional Logic & Dates | C61: Date & Time Functions | D61: Q5 | E61: 1193. Monthly Transactions I | F61: LeetCode | G61: Challenging (LeetCode: Medium) | H61: =HYPERLINK("https://leetcode.com/problems/monthly-transactions-i/","https://leetcode.com/problems/monthly-transactions-i/") -> https://leetcode.com/problems/monthly-transactions-i/ | I61: Yes – free problem (not Premium); free LeetCode account to submit | J61: DATE_FORMAT month key with conditional counts and sums | K61: T9 GROUP BY, T11 CASE inside aggregates | L61: Yes – DATE_FORMAT(trans_date, '%Y-%m') ... SUM(CASE ...) GROUP BY month, country | M61: Added (verified) | N61: =IF(M61="Added (verified)","Yes","No") -> Yes | O61: I13 | P61: Engines: MySQL, MS SQL Server, Oracle, PostgreSQL.
A62: 13 | B62: Conditional Logic & Dates | C62: Pivoting & Conditional Aggregation | D62: Q1 | E62: 1179. Reformat Department Table | F62: LeetCode | G62: Easy (LeetCode: Easy) | H62: =HYPERLINK("https://leetcode.com/problems/reformat-department-table/","https://leetcode.com/problems/reformat-department-table/") -> https://leetcode.com/problems/reformat-department-table/ | I62: Yes – free problem (not Premium); free LeetCode account to submit | J62: Pivot rows into month columns with SUM(CASE ...) | K62: T9 GROUP BY, T11 CASE | L62: Yes – one SUM(CASE WHEN month = 'Jan' ...) column per month, GROUP BY id | M62: Added (verified) | N62: =IF(M62="Added (verified)","Yes","No") -> Yes | O62: E14 | P62: Engines: MySQL, MS SQL Server, Oracle, PostgreSQL.
A63: 13 | B63: Conditional Logic & Dates | C63: Pivoting & Conditional Aggregation | D63: Q2 | E63: 1211. Queries Quality and Percentage | F63: LeetCode | G63: Easy (LeetCode: Easy) | H63: =HYPERLINK("https://leetcode.com/problems/queries-quality-and-percentage/","https://leetcode.com/problems/queries-quality-and-percentage/") -> https://leetcode.com/problems/queries-quality-and-percentage/ | I63: Yes – free problem (not Premium); free LeetCode account to submit | J63: Average of a ratio + percentage of rows meeting a condition | K63: T8 ROUND, T9 GROUP BY, T11 CASE | L63: Yes – ROUND(AVG(rating / position), 2) and ROUND(AVG(CASE WHEN rating < 3 THEN 1 ELSE 0 END) * 100, 2) | M63: Added (verified) | N63: =IF(M63="Added (verified)","Yes","No") -> Yes | O63: F14 | P63: Engines: MySQL, MS SQL Server, Oracle, PostgreSQL.
A64: 13 | B64: Conditional Logic & Dates | C64: Pivoting & Conditional Aggregation | D64: Q3 | E64: Combining Aggregates (GSQ84) | F64: CodeChef | G64: Medium (CodeChef: medium) | H64: =HYPERLINK("https://www.codechef.com/learn/course/sql-intermediate/SQ00BS08/problems/GSQ84","https://www.codechef.com/learn/course/sql-intermediate/SQ00BS08/problems/GSQ84") -> https://www.codechef.com/learn/course/sql-intermediate/SQ00BS08/problems/GSQ84 | I64: Yes – free (non-Pro) lesson of CodeChef 'Learn Advanced SQL'; free account to submit | J64: Ratio of a conditional SUM to the total SUM per group | K64: T9 GROUP BY, T11 CASE | L64: Yes – 100 * SUM(CASE ...) / SUM(Fee) ... GROUP BY Department | M64: Added (verified) | N64: =IF(M64="Added (verified)","Yes","No") -> Yes | O64: G14 | P64: Runs on SQLite.
A65: 13 | B65: Conditional Logic & Dates | C65: Pivoting & Conditional Aggregation | D65: Q4 | E65: 1393. Capital Gain/Loss | F65: LeetCode | G65: Medium (LeetCode: Medium) | H65: =HYPERLINK("https://leetcode.com/problems/capital-gainloss/","https://leetcode.com/problems/capital-gainloss/") -> https://leetcode.com/problems/capital-gainloss/ | I65: Yes – free problem (not Premium); free LeetCode account to submit | J65: Signed SUM(CASE ...) to net buys against sells | K65: T9 GROUP BY, T11 CASE | L65: Yes – SUM(CASE WHEN operation = 'Buy' THEN -price ELSE price END) ... GROUP BY stock_name | M65: Added (verified) | N65: =IF(M65="Added (verified)","Yes","No") -> Yes | O65: H14 | P65: Engines: MySQL, MS SQL Server, Oracle, PostgreSQL.
A66: 13 | B66: Conditional Logic & Dates | C66: Pivoting & Conditional Aggregation | D66: Q5 | E66: 3220. Odd and Even Transactions | F66: LeetCode | G66: Challenging (LeetCode: Medium) | H66: =HYPERLINK("https://leetcode.com/problems/odd-and-even-transactions/","https://leetcode.com/problems/odd-and-even-transactions/") -> https://leetcode.com/problems/odd-and-even-transactions/ | I66: Yes – free problem (not Premium); free LeetCode account to submit | J66: Two conditional SUM columns per date | K66: T4 ORDER BY, T8 MOD, T11 CASE | L66: Yes – SUM(CASE WHEN MOD(amount, 2) = 1 ...) and SUM(CASE WHEN MOD(amount, 2) = 0 ...) GROUP BY transaction_date | M66: Added (verified) | N66: =IF(M66="Added (verified)","Yes","No") -> Yes | O66: I14 | P66: Engines: MySQL, MS SQL Server, Oracle, PostgreSQL.
A67: 14 | B67: Data Modification & Schema | C67: UPDATE & DELETE | D67: Q1 | E67: Practice Problem - Update table (GSQ11) | F67: CodeChef | G67: Easy (CodeChef: easy) | H67: =HYPERLINK("https://www.codechef.com/learn/course/sql/SQ00LS02/problems/GSQ11","https://www.codechef.com/learn/course/sql/SQ00LS02/problems/GSQ11") -> https://www.codechef.com/learn/course/sql/SQ00LS02/problems/GSQ11 | I67: Yes – free (non-Pro) lesson of CodeChef 'Learn SQL'; free account to submit | J67: UPDATE ... SET ... WHERE | K67: T1 SELECT, T3 WHERE | L67: Yes – UPDATE employee SET Hourly_Pay = 150 WHERE Department = 'Hr' | M67: Added (verified) | N67: =IF(M67="Added (verified)","Yes","No") -> Yes | O67: E15 | P67: Runs on SQLite.
A68: 14 | B68: Data Modification & Schema | C68: UPDATE & DELETE | D68: Q2 | E68: Practice - Delete Single Record (GSQ56) | F68: CodeChef | G68: Easy (CodeChef: easy) | H68: =HYPERLINK("https://www.codechef.com/learn/course/sql/SQ00LS03/problems/GSQ56","https://www.codechef.com/learn/course/sql/SQ00LS03/problems/GSQ56") -> https://www.codechef.com/learn/course/sql/SQ00LS03/problems/GSQ56 | I68: Yes – free (non-Pro) lesson of CodeChef 'Learn SQL'; free account to submit | J68: DELETE one row by key | K68: T1 SELECT, T3 WHERE | L68: Yes – DELETE FROM customer WHERE Id = 1 | M68: Added (verified) | N68: =IF(M68="Added (verified)","Yes","No") -> Yes | O68: F15 | P68: Runs on SQLite.
A69: 14 | B69: Data Modification & Schema | C69: UPDATE & DELETE | D69: Q3 | E69: Practice - Delete From (GSQ14) | F69: CodeChef | G69: Easy (CodeChef: easy) | H69: =HYPERLINK("https://www.codechef.com/learn/course/sql/SQ00LS02/problems/GSQ14","https://www.codechef.com/learn/course/sql/SQ00LS02/problems/GSQ14") -> https://www.codechef.com/learn/course/sql/SQ00LS02/problems/GSQ14 | I69: Yes – free (non-Pro) lesson of CodeChef 'Learn SQL'; free account to submit | J69: DELETE rows matching a condition | K69: T1 SELECT, T3 WHERE | L69: Yes – DELETE FROM employee WHERE Department = 'Client' | M69: Added (verified) | N69: =IF(M69="Added (verified)","Yes","No") -> Yes | O69: G15 | P69: Runs on SQLite.
A70: 14 | B70: Data Modification & Schema | C70: UPDATE & DELETE | D70: Q4 | E70: Task-4C Data Modification (Update and Alter) (RSMSPR04C) | F70: CodeChef | G70: Medium (CodeChef: easy) | H70: =HYPERLINK("https://www.codechef.com/learn/course/sql/BEGSQLPR/problems/RSMSPR04C","https://www.codechef.com/learn/course/sql/BEGSQLPR/problems/RSMSPR04C") -> https://www.codechef.com/learn/course/sql/BEGSQLPR/problems/RSMSPR04C | I70: Yes – free (non-Pro) lesson of CodeChef 'Learn SQL'; free account to submit | J70: UPDATE, then check the result with a filtered SELECT | K70: T3 WHERE | L70: Yes – UPDATE ... SET stock_quantity = 0 WHERE stock_quantity = 10, then SELECT ... WHERE | M70: Added (verified) | N70: =IF(M70="Added (verified)","Yes","No") -> Yes | O70: H15 | P70: Lesson of the free 'Retail store management system' project; the tables it needs are pre-loaded and shown in the statement. Runs on SQLite.
A71: 14 | B71: Data Modification & Schema | C71: UPDATE & DELETE | D71: Q5 | E71: 627. Swap Sex of Employees | F71: LeetCode | G71: Medium (LeetCode: Easy) | H71: =HYPERLINK("https://leetcode.com/problems/swap-sex-of-employees/","https://leetcode.com/problems/swap-sex-of-employees/") -> https://leetcode.com/problems/swap-sex-of-employees/ | I71: Yes – free problem (not Premium); free LeetCode account to submit | J71: Single UPDATE using CASE (no SELECT, no temp table) | K71: T11 CASE | L71: Yes – UPDATE Salary SET sex = CASE sex WHEN 'm' THEN 'f' ELSE 'm' END | M71: Added (verified) | N71: =IF(M71="Added (verified)","Yes","No") -> Yes | O71: I15 | P71: Engines: MySQL, MS SQL Server, Oracle, PostgreSQL.
A72: 15 | B72: Data Modification & Schema | C72: ALTER TABLE & Constraints | D72: Q1 | E72: Practice Problem - Alter table (GSQ10) | F72: CodeChef | G72: Easy (CodeChef: easy) | H72: =HYPERLINK("https://www.codechef.com/learn/course/sql/SQ00LS02/problems/GSQ10","https://www.codechef.com/learn/course/sql/SQ00LS02/problems/GSQ10") -> https://www.codechef.com/learn/course/sql/SQ00LS02/problems/GSQ10 | I72: Yes – free (non-Pro) lesson of CodeChef 'Learn SQL'; free account to submit | J72: ALTER TABLE ... ADD COLUMN ... DEFAULT | K72: T1 SELECT, T2 CREATE TABLE | L72: Yes – ALTER TABLE employee ADD COLUMN Hourly_Pay INT DEFAULT 100 | M72: Added (verified) | N72: =IF(M72="Added (verified)","Yes","No") -> Yes | O72: E16 | P72: Runs on SQLite.
A73: 15 | B73: Data Modification & Schema | C73: ALTER TABLE & Constraints | D73: Q2 | E73: Constraints (GSQ13) | F73: CodeChef | G73: Easy (CodeChef: easy) | H73: =HYPERLINK("https://www.codechef.com/learn/course/sql/SQ00LS02/problems/GSQ13","https://www.codechef.com/learn/course/sql/SQ00LS02/problems/GSQ13") -> https://www.codechef.com/learn/course/sql/SQ00LS02/problems/GSQ13 | I73: Yes – free (non-Pro) lesson of CodeChef 'Learn SQL'; free account to submit | J73: PRIMARY KEY, UNIQUE, NOT NULL, CHECK | K73: T2 CREATE TABLE, T5 IN | L73: Yes – one CREATE TABLE with four constraint types | M73: Added (verified) | N73: =IF(M73="Added (verified)","Yes","No") -> Yes | O73: F16 | P73: Runs on SQLite.
A74: 15 | B74: Data Modification & Schema | C74: ALTER TABLE & Constraints | D74: Q3 | E74: Practice - Create Table with Constraints (GSQ57) | F74: CodeChef | G74: Medium (CodeChef: easy) | H74: =HYPERLINK("https://www.codechef.com/learn/course/sql/SQ00LS03/problems/GSQ57","https://www.codechef.com/learn/course/sql/SQ00LS03/problems/GSQ57") -> https://www.codechef.com/learn/course/sql/SQ00LS03/problems/GSQ57 | I74: Yes – free (non-Pro) lesson of CodeChef 'Learn SQL'; free account to submit | J74: Fixing a script that breaks PRIMARY KEY / UNIQUE rules | K74: T2 CREATE TABLE & INSERT | L74: Yes – corrected CREATE TABLE with PK / UNIQUE and valid INSERT rows | M74: Added (verified) | N74: =IF(M74="Added (verified)","Yes","No") -> Yes | O74: G16 | P74: Runs on SQLite.
A75: 15 | B75: Data Modification & Schema | C75: ALTER TABLE & Constraints | D75: Q4 | E75: Foreign Key and Unique Key (SQLKEY01) | F75: CodeChef | G75: Medium (CodeChef: easy) | H75: =HYPERLINK("https://www.codechef.com/learn/course/sql-intermediate/SQ00BS02/problems/SQLKEY01","https://www.codechef.com/learn/course/sql-intermediate/SQ00BS02/problems/SQLKEY01") -> https://www.codechef.com/learn/course/sql-intermediate/SQ00BS02/problems/SQLKEY01 | I75: Yes – free (non-Pro) lesson of CodeChef 'Learn Advanced SQL'; free account to submit | J75: FOREIGN KEY ... REFERENCES + UNIQUE | K75: T2 CREATE TABLE | L75: Yes – two CREATE TABLE statements linked by a foreign key | M75: Added (verified) | N75: =IF(M75="Added (verified)","Yes","No") -> Yes | O75: H16 | P75: Runs on SQLite.
A76: 15 | B76: Data Modification & Schema | C76: ALTER TABLE & Constraints | D76: Q5 | E76: Task-1 Design the Database Schema- Tables & Fields (RSMSPR01) | F76: CodeChef | G76: Challenging (CodeChef: medium) | H76: =HYPERLINK("https://www.codechef.com/learn/course/sql/BEGSQLPR/problems/RSMSPR01","https://www.codechef.com/learn/course/sql/BEGSQLPR/problems/RSMSPR01") -> https://www.codechef.com/learn/course/sql/BEGSQLPR/problems/RSMSPR01 | I76: Yes – free (non-Pro) lesson of CodeChef 'Learn SQL'; free account to submit | J76: Full schema with PK, FK, UNIQUE, NOT NULL, CHECK and DEFAULT | K76: T2 CREATE TABLE, T5 IN | L76: Yes – CREATE TABLE statements with constraints only | M76: Added (verified) | N76: =IF(M76="Added (verified)","Yes","No") -> Yes | O76: I16 | P76: Lesson of the free 'Retail store management system' project; the tables it needs are pre-loaded and shown in the statement. Runs on SQLite.
A77: 16 | B77: Joins | C77: INNER JOIN | D77: Q1 | E77: 1068. Product Sales Analysis I | F77: LeetCode | G77: Easy (LeetCode: Easy) | H77: =HYPERLINK("https://leetcode.com/problems/product-sales-analysis-i/","https://leetcode.com/problems/product-sales-analysis-i/") -> https://leetcode.com/problems/product-sales-analysis-i/ | I77: Yes – free problem (not Premium); free LeetCode account to submit | J77: Two-table INNER JOIN | K77: T1 SELECT | L77: Yes – Sales JOIN Product ON product_id | M77: Added (verified) | N77: =IF(M77="Added (verified)","Yes","No") -> Yes | O77: E17 | P77: Engines: MySQL, MS SQL Server, Oracle, PostgreSQL.
A78: 16 | B78: Joins | C78: INNER JOIN | D78: Q2 | E78: African Cities | F78: HackerRank | G78: Easy (HackerRank: Easy) | H78: =HYPERLINK("https://www.hackerrank.com/challenges/african-cities/problem","https://www.hackerrank.com/challenges/african-cities/problem") -> https://www.hackerrank.com/challenges/african-cities/problem | I78: Yes – free; free HackerRank account to submit | J78: INNER JOIN + WHERE on the joined table | K78: T3 WHERE | L78: Yes – CITY JOIN COUNTRY ON CountryCode = Code WHERE Continent = 'Africa' | M78: Added (verified) | N78: =IF(M78="Added (verified)","Yes","No") -> Yes | O78: F17 | P78: Engines: MySQL, MS SQL Server, Oracle (no DB2).
A79: 16 | B79: Joins | C79: INNER JOIN | D79: Q3 | E79: Inner Joins (GSQ62) | F79: CodeChef | G79: Easy (CodeChef: easy) | H79: =HYPERLINK("https://www.codechef.com/learn/course/sql-intermediate/SQ00BS01/problems/GSQ62","https://www.codechef.com/learn/course/sql-intermediate/SQ00BS01/problems/GSQ62") -> https://www.codechef.com/learn/course/sql-intermediate/SQ00BS01/problems/GSQ62 | I79: Yes – free (non-Pro) lesson of CodeChef 'Learn Advanced SQL'; free account to submit | J79: JOIN ... ON a matching key | K79: T1 SELECT | L79: Yes – student JOIN course ON Course_id | M79: Added (verified) | N79: =IF(M79="Added (verified)","Yes","No") -> Yes | O79: G17 | P79: Runs on SQLite.
A80: 16 | B80: Joins | C80: INNER JOIN | D80: Q4 | E80: The Report | F80: HackerRank | G80: Medium (HackerRank: Medium) | H80: =HYPERLINK("https://www.hackerrank.com/challenges/the-report/problem","https://www.hackerrank.com/challenges/the-report/problem") -> https://www.hackerrank.com/challenges/the-report/problem | I80: Yes – free; free HackerRank account to submit | J80: Non-equi JOIN (BETWEEN) + CASE to hide names | K80: T4 ORDER BY, T5 BETWEEN, T11 CASE | L80: Yes – JOIN Grades ON Marks BETWEEN Min_Mark AND Max_Mark, CASE for grades below 8 | M80: Added (verified) | N80: =IF(M80="Added (verified)","Yes","No") -> Yes | O80: H17 | P80: Engines: MySQL, MS SQL Server, Oracle, DB2.
A81: 16 | B81: Joins | C81: INNER JOIN | D81: Q5 | E81: Top Competitors | F81: HackerRank | G81: Challenging (HackerRank: Medium) | H81: =HYPERLINK("https://www.hackerrank.com/challenges/full-score/problem","https://www.hackerrank.com/challenges/full-score/problem") -> https://www.hackerrank.com/challenges/full-score/problem | I81: Yes – free; free HackerRank account to submit | J81: Four-table join + GROUP BY / HAVING | K81: T4 ORDER BY, T9 GROUP BY, T10 HAVING | L81: Yes – joins on hacker, challenge and difficulty, HAVING COUNT(*) > 1 | M81: Added (verified) | N81: =IF(M81="Added (verified)","Yes","No") -> Yes | O81: I17 | P81: Engines: MySQL, MS SQL Server, Oracle, DB2.
A82: 17 | B82: Joins | C82: LEFT / RIGHT / FULL OUTER JOIN | D82: Q1 | E82: 175. Combine Two Tables | F82: LeetCode | G82: Easy (LeetCode: Easy) | H82: =HYPERLINK("https://leetcode.com/problems/combine-two-tables/","https://leetcode.com/problems/combine-two-tables/") -> https://leetcode.com/problems/combine-two-tables/ | I82: Yes – free problem (not Premium); free LeetCode account to submit | J82: LEFT JOIN keeping unmatched rows | K82: T16 JOIN | L82: Yes – Person LEFT JOIN Address ON personId | M82: Added (verified) | N82: =IF(M82="Added (verified)","Yes","No") -> Yes | O82: E18 | P82: Engines: MySQL, MS SQL Server, Oracle, PostgreSQL.
A83: 17 | B83: Joins | C83: LEFT / RIGHT / FULL OUTER JOIN | D83: Q2 | E83: 1378. Replace Employee ID With The Unique Identifier | F83: LeetCode | G83: Easy (LeetCode: Easy) | H83: =HYPERLINK("https://leetcode.com/problems/replace-employee-id-with-the-unique-identifier/","https://leetcode.com/problems/replace-employee-id-with-the-unique-identifier/") -> https://leetcode.com/problems/replace-employee-id-with-the-unique-identifier/ | I83: Yes – free problem (not Premium); free LeetCode account to submit | J83: LEFT JOIN returning NULL where no match | K83: T16 JOIN | L83: Yes – Employees LEFT JOIN EmployeeUNI ON id | M83: Added (verified) | N83: =IF(M83="Added (verified)","Yes","No") -> Yes | O83: F18 | P83: Engines: MySQL, MS SQL Server, Oracle, PostgreSQL.
A84: 17 | B84: Joins | C84: LEFT / RIGHT / FULL OUTER JOIN | D84: Q3 | E84: Full Outer Joins (ASQL01B) | F84: CodeChef | G84: Medium (CodeChef: medium) | H84: =HYPERLINK("https://www.codechef.com/learn/course/sql-intermediate/SQ00BS01/problems/ASQL01B","https://www.codechef.com/learn/course/sql-intermediate/SQ00BS01/problems/ASQL01B") -> https://www.codechef.com/learn/course/sql-intermediate/SQ00BS01/problems/ASQL01B | I84: Yes – free (non-Pro) lesson of CodeChef 'Learn Advanced SQL'; free account to submit | J84: FULL OUTER JOIN | K84: T16 JOIN | L84: Yes – student FULL OUTER JOIN course ON Course_id | M84: Added (verified) | N84: =IF(M84="Added (verified)","Yes","No") -> Yes | O84: G18 | P84: Runs on SQLite.
A85: 17 | B85: Joins | C85: LEFT / RIGHT / FULL OUTER JOIN | D85: Q4 | E85: 1581. Customer Who Visited but Did Not Make Any Transactions | F85: LeetCode | G85: Medium (LeetCode: Easy) | H85: =HYPERLINK("https://leetcode.com/problems/customer-who-visited-but-did-not-make-any-transactions/","https://leetcode.com/problems/customer-who-visited-but-did-not-make-any-transactions/") -> https://leetcode.com/problems/customer-who-visited-but-did-not-make-any-transactions/ | I85: Yes – free problem (not Premium); free LeetCode account to submit | J85: LEFT JOIN ... IS NULL (anti-join) + COUNT per customer | K85: T3 IS NULL, T9 GROUP BY | L85: Yes – Visits LEFT JOIN Transactions ... WHERE transaction_id IS NULL GROUP BY customer_id | M85: Added (verified) | N85: =IF(M85="Added (verified)","Yes","No") -> Yes | O85: H18 | P85: Engines: MySQL, MS SQL Server, Oracle, PostgreSQL.
A86: 17 | B86: Joins | C86: LEFT / RIGHT / FULL OUTER JOIN | D86: Q5 | E86: 1251. Average Selling Price | F86: LeetCode | G86: Challenging (LeetCode: Easy) | H86: =HYPERLINK("https://leetcode.com/problems/average-selling-price/","https://leetcode.com/problems/average-selling-price/") -> https://leetcode.com/problems/average-selling-price/ | I86: Yes – free problem (not Premium); free LeetCode account to submit | J86: LEFT JOIN on a date-range condition + weighted average + IFNULL | K86: T5 BETWEEN, T8 ROUND, T9 GROUP BY | L86: Yes – LEFT JOIN UnitsSold ON product_id AND purchase_date BETWEEN start_date AND end_date | M86: Added (verified) | N86: =IF(M86="Added (verified)","Yes","No") -> Yes | O86: I18 | P86: Engines: MySQL, MS SQL Server, Oracle, PostgreSQL.
A87: 18 | B87: Joins | C87: SELF JOIN & CROSS JOIN | D87: Q1 | E87: 181. Employees Earning More Than Their Managers | F87: LeetCode | G87: Easy (LeetCode: Easy) | H87: =HYPERLINK("https://leetcode.com/problems/employees-earning-more-than-their-managers/","https://leetcode.com/problems/employees-earning-more-than-their-managers/") -> https://leetcode.com/problems/employees-earning-more-than-their-managers/ | I87: Yes – free problem (not Premium); free LeetCode account to submit | J87: SELF JOIN with table aliases | K87: T16 JOIN | L87: Yes – Employee e JOIN Employee m ON e.managerId = m.id WHERE e.salary > m.salary | M87: Added (verified) | N87: =IF(M87="Added (verified)","Yes","No") -> Yes | O87: E19 | P87: Engines: MySQL, MS SQL Server, Oracle, PostgreSQL.
A88: 18 | B88: Joins | C88: SELF JOIN & CROSS JOIN | D88: Q2 | E88: Self Joins (ASQL01C) | F88: CodeChef | G88: Easy (CodeChef: easy) | H88: =HYPERLINK("https://www.codechef.com/learn/course/sql-intermediate/SQ00BS01/problems/ASQL01C","https://www.codechef.com/learn/course/sql-intermediate/SQ00BS01/problems/ASQL01C") -> https://www.codechef.com/learn/course/sql-intermediate/SQ00BS01/problems/ASQL01C | I88: Yes – free (non-Pro) lesson of CodeChef 'Learn Advanced SQL'; free account to submit | J88: SELF JOIN to pair rows of one table | K88: T4 DISTINCT / ORDER BY, T16 JOIN | L88: Yes – student s1 JOIN student s2 on department / course, s1.St_id != s2.St_id | M88: Added (verified) | N88: =IF(M88="Added (verified)","Yes","No") -> Yes | O88: F19 | P88: Runs on SQLite.
A89: 18 | B89: Joins | C89: SELF JOIN & CROSS JOIN | D89: Q3 | E89: 1280. Students and Examinations | F89: LeetCode | G89: Medium (LeetCode: Easy) | H89: =HYPERLINK("https://leetcode.com/problems/students-and-examinations/","https://leetcode.com/problems/students-and-examinations/") -> https://leetcode.com/problems/students-and-examinations/ | I89: Yes – free problem (not Premium); free LeetCode account to submit | J89: CROSS JOIN to build every pair, then LEFT JOIN + COUNT | K89: T9 GROUP BY, T17 LEFT JOIN | L89: Yes – Students CROSS JOIN Subjects LEFT JOIN Examinations ... GROUP BY | M89: Added (verified) | N89: =IF(M89="Added (verified)","Yes","No") -> Yes | O89: G19 | P89: Engines: MySQL, MS SQL Server, Oracle, PostgreSQL.
A90: 18 | B90: Joins | C90: SELF JOIN & CROSS JOIN | D90: Q4 | E90: 197. Rising Temperature | F90: LeetCode | G90: Medium (LeetCode: Easy) | H90: =HYPERLINK("https://leetcode.com/problems/rising-temperature/","https://leetcode.com/problems/rising-temperature/") -> https://leetcode.com/problems/rising-temperature/ | I90: Yes – free problem (not Premium); free LeetCode account to submit | J90: SELF JOIN on consecutive dates | K90: T12 DATEDIFF / DATE_ADD | L90: Yes – Weather w1 JOIN Weather w2 ON DATEDIFF(w1.recordDate, w2.recordDate) = 1 | M90: Added (verified) | N90: =IF(M90="Added (verified)","Yes","No") -> Yes | O90: H19 | P90: Engines: MySQL, MS SQL Server, Oracle, PostgreSQL.
A91: 18 | B91: Joins | C91: SELF JOIN & CROSS JOIN | D91: Q5 | E91: Symmetric Pairs | F91: HackerRank | G91: Challenging (HackerRank: Medium) | H91: =HYPERLINK("https://www.hackerrank.com/challenges/symmetric-pairs/problem","https://www.hackerrank.com/challenges/symmetric-pairs/problem") -> https://www.hackerrank.com/challenges/symmetric-pairs/problem | I91: Yes – free; free HackerRank account to submit | J91: SELF JOIN on swapped columns + HAVING for the X = Y case | K91: T4 ORDER BY, T9 GROUP BY, T10 HAVING | L91: Yes – self join on X = Y and Y = X with GROUP BY / HAVING; UNION not required | M91: Added (verified) | N91: =IF(M91="Added (verified)","Yes","No") -> Yes | O91: I19 | P91: Engines: MySQL, MS SQL Server, Oracle, DB2.
A92: 19 | B92: Subqueries & Set Operations | C92: Subqueries | D92: Q1 | E92: 1978. Employees Whose Manager Left the Company | F92: LeetCode | G92: Easy (LeetCode: Easy) | H92: =HYPERLINK("https://leetcode.com/problems/employees-whose-manager-left-the-company/","https://leetcode.com/problems/employees-whose-manager-left-the-company/") -> https://leetcode.com/problems/employees-whose-manager-left-the-company/ | I92: Yes – free problem (not Premium); free LeetCode account to submit | J92: NOT IN (subquery) | K92: T3 WHERE, T4 ORDER BY | L92: Yes – WHERE salary < 30000 AND manager_id NOT IN (SELECT employee_id FROM Employees) | M92: Added (verified) | N92: =IF(M92="Added (verified)","Yes","No") -> Yes | O92: E20 | P92: Engines: MySQL, MS SQL Server, Oracle, PostgreSQL.
A93: 19 | B93: Subqueries & Set Operations | C93: Subqueries | D93: Q2 | E93: Problem - Non-Correlated Subqueries (GSQ71) | F93: CodeChef | G93: Easy (CodeChef: medium) | H93: =HYPERLINK("https://www.codechef.com/learn/course/sql-intermediate/SQ00BS04/problems/GSQ71","https://www.codechef.com/learn/course/sql-intermediate/SQ00BS04/problems/GSQ71") -> https://www.codechef.com/learn/course/sql-intermediate/SQ00BS04/problems/GSQ71 | I93: Yes – free (non-Pro) lesson of CodeChef 'Learn Advanced SQL'; free account to submit | J93: Scalar subquery compared with each row | K93: T7 AVG | L93: Yes – WHERE f_cost > (SELECT AVG(f_cost) FROM food) | M93: Added (verified) | N93: =IF(M93="Added (verified)","Yes","No") -> Yes | O93: F20 | P93: Runs on SQLite.
A94: 19 | B94: Subqueries & Set Operations | C94: Subqueries | D94: Q3 | E94: Binary Tree Nodes | F94: HackerRank | G94: Medium (HackerRank: Medium) | H94: =HYPERLINK("https://www.hackerrank.com/challenges/binary-search-tree-1/problem","https://www.hackerrank.com/challenges/binary-search-tree-1/problem") -> https://www.hackerrank.com/challenges/binary-search-tree-1/problem | I94: Yes – free; free HackerRank account to submit | J94: CASE with an IN (subquery) test | K94: T4 ORDER BY, T11 CASE | L94: Yes – CASE WHEN P IS NULL THEN 'Root' WHEN N IN (SELECT P FROM BST) THEN 'Inner' ELSE 'Leaf' END | M94: Added (verified) | N94: =IF(M94="Added (verified)","Yes","No") -> Yes | O94: G20 | P94: Engines: MySQL, MS SQL Server, Oracle, DB2.
A95: 19 | B95: Subqueries & Set Operations | C95: Subqueries | D95: Q4 | E95: 176. Second Highest Salary | F95: LeetCode | G95: Medium (LeetCode: Medium) | H95: =HYPERLINK("https://leetcode.com/problems/second-highest-salary/","https://leetcode.com/problems/second-highest-salary/") -> https://leetcode.com/problems/second-highest-salary/ | I95: Yes – free problem (not Premium); free LeetCode account to submit | J95: Scalar subquery that returns NULL when there is no answer | K95: T7 MAX | L95: Yes – SELECT MAX(salary) ... WHERE salary < (SELECT MAX(salary) FROM Employee) | M95: Added (verified) | N95: =IF(M95="Added (verified)","Yes","No") -> Yes | O95: H20 | P95: Engines: MySQL, MS SQL Server, Oracle, PostgreSQL.
A96: 19 | B96: Subqueries & Set Operations | C96: Subqueries | D96: Q5 | E96: 1045. Customers Who Bought All Products | F96: LeetCode | G96: Challenging (LeetCode: Medium) | H96: =HYPERLINK("https://leetcode.com/problems/customers-who-bought-all-products/","https://leetcode.com/problems/customers-who-bought-all-products/") -> https://leetcode.com/problems/customers-who-bought-all-products/ | I96: Yes – free problem (not Premium); free LeetCode account to submit | J96: Subquery inside HAVING (relational division) | K96: T9 GROUP BY, T10 HAVING | L96: Yes – HAVING COUNT(DISTINCT product_key) = (SELECT COUNT(*) FROM Product) | M96: Added (verified) | N96: =IF(M96="Added (verified)","Yes","No") -> Yes | O96: I20 | P96: Engines: MySQL, MS SQL Server, Oracle, PostgreSQL.
A97: 20 | B97: Subqueries & Set Operations | C97: Correlated Subqueries & EXISTS | D97: Q1 | E97: 183. Customers Who Never Order | F97: LeetCode | G97: Easy (LeetCode: Easy) | H97: =HYPERLINK("https://leetcode.com/problems/customers-who-never-order/","https://leetcode.com/problems/customers-who-never-order/") -> https://leetcode.com/problems/customers-who-never-order/ | I97: Yes – free problem (not Premium); free LeetCode account to submit | J97: NOT EXISTS (anti-join) | K97: T1 AS, T3 WHERE | L97: Yes – WHERE NOT EXISTS (SELECT 1 FROM Orders o WHERE o.customerId = c.id) | M97: Added (verified) | N97: =IF(M97="Added (verified)","Yes","No") -> Yes | O97: E21 | P97: Engines: MySQL, MS SQL Server, Oracle, PostgreSQL.
A98: 20 | B98: Subqueries & Set Operations | C98: Correlated Subqueries & EXISTS | D98: Q2 | E98: 184. Department Highest Salary | F98: LeetCode | G98: Medium (LeetCode: Medium) | H98: =HYPERLINK("https://leetcode.com/problems/department-highest-salary/","https://leetcode.com/problems/department-highest-salary/") -> https://leetcode.com/problems/department-highest-salary/ | I98: Yes – free problem (not Premium); free LeetCode account to submit | J98: Correlated MAX per department | K98: T7 MAX, T16 JOIN | L98: Yes – WHERE e.salary = (SELECT MAX(salary) FROM Employee WHERE departmentId = e.departmentId) | M98: Added (verified) | N98: =IF(M98="Added (verified)","Yes","No") -> Yes | O98: F21 | P98: Engines: MySQL, MS SQL Server, Oracle, PostgreSQL.
A99: 20 | B99: Subqueries & Set Operations | C99: Correlated Subqueries & EXISTS | D99: Q3 | E99: 1164. Product Price at a Given Date | F99: LeetCode | G99: Medium (LeetCode: Medium) | H99: =HYPERLINK("https://leetcode.com/problems/product-price-at-a-given-date/","https://leetcode.com/problems/product-price-at-a-given-date/") -> https://leetcode.com/problems/product-price-at-a-given-date/ | I99: Yes – free problem (not Premium); free LeetCode account to submit | J99: Correlated scalar subquery with a default value | K99: T4 DISTINCT / ORDER BY / LIMIT, T17 IFNULL / COALESCE | L99: Yes – COALESCE((latest new_price on or before 2019-08-16 for this product), 10); UNION not required | M99: Added (verified) | N99: =IF(M99="Added (verified)","Yes","No") -> Yes | O99: G21 | P99: Engines: MySQL, MS SQL Server, Oracle, PostgreSQL.
A100: 20 | B100: Subqueries & Set Operations | C100: Correlated Subqueries & EXISTS | D100: Q4 | E100: Ollivander's Inventory | F100: HackerRank | G100: Challenging (HackerRank: Medium) | H100: =HYPERLINK("https://www.hackerrank.com/challenges/harry-potter-and-wands/problem","https://www.hackerrank.com/challenges/harry-potter-and-wands/problem") -> https://www.hackerrank.com/challenges/harry-potter-and-wands/problem | I100: Yes – free; free HackerRank account to submit | J100: Correlated MIN per (power, age) inside a join | K100: T4 ORDER BY, T16 JOIN | L100: Yes – coins_needed = (SELECT MIN(...) ... WHERE same power AND same age) | M100: Added (verified) | N100: =IF(M100="Added (verified)","Yes","No") -> Yes | O100: H21 | P100: Engines: MySQL, MS SQL Server, Oracle, DB2.
...

Sheet Validation Report
A1: SQL Question Bank – Validation Report
A2: Checked on 3–4 Oct 2026 against each platform's live problem data. The learning sequence is the row order of 'SQL Practice Links' (Topic 1 = SELECT & Column Aliases ... Topic 26 = Stored Functions & Procedures). Every listed problem is free, appears only once, and needs only its own topic and earlier ones.
A4: Summary
B5: Topics covered | D5: =COUNTA('SQL Practice Links'!C2:C27) -> 26 | E5: Grouped into 7 sections, from SQL basics to advanced SQL.
B6: Problem slots (topics x 5) | D6: =COUNTA('Question Bank Details'!$A$2:$A$131) -> 130 | E6: Five problems per topic, ordered Q1 (easiest) to Q5 (hardest).
B7: Problems added (verified) | D7: =COUNTIF('Question Bank Details'!$M$2:$M$131,"Added (verified)") -> 125 | E7: Each one opened live: exists, free, title and difficulty confirmed.
B8: Slots with no suitable free problem | D8: =COUNTIF('Question Bank Details'!$M$2:$M$131,"Not available") -> 5 | E8: Grey cells in 'SQL Practice Links'; reasons are listed below.
B9: Topics with all 5 problems | D9: =COUNTIF($D$24:$D$49,5) -> 24
B10: Topics short of 5 | D10: =COUNTIF($D$24:$D$49,"<5") -> 2 | E10: Recursive CTEs (4) and Stored Functions & Procedures (1).
B11: Duplicate problem links | D11: =SUMPRODUCT(('Question Bank Details'!$H$2:$H$131<>"-")*(COUNTIF('Question Bank Details'!$H$2:$H$131,'Question Bank Details'!$H$2:$H$131)>1)) -> 0 | E11: Each problem is used in exactly one topic.
B12: Links that could not be verified as free | D12: =COUNTIF('Question Bank Details'!$I$2:$I$131,"Not verifiable*") -> 0
B14: Problems by platform
B15: LeetCode | D15: =COUNTIF('Question Bank Details'!$F$2:$F$131,"LeetCode") -> 52 | E15: Free Database problems only (Premium excluded).
B16: HackerRank | D16: =COUNTIF('Question Bank Details'!$F$2:$F$131,"HackerRank") -> 29 | E16: SQL domain challenges (all free).
B17: CodeChef | D17: =COUNTIF('Question Bank Details'!$F$2:$F$131,"CodeChef") -> 44 | E17: Free, non-Pro lessons of 'Learn SQL', 'Learn Advanced SQL' and 'SQL Practice Queries'.
B18: Codeforces | D18: =COUNTIF('Question Bank Details'!$F$2:$F$131,"Codeforces") -> 0 | E18: No SQL problems exist on Codeforces (its problem set has no database / SQL tasks).
B19: GeeksforGeeks | D19: =COUNTIF('Question Bank Details'!$F$2:$F$131,"GeeksforGeeks") -> 0 | E19: No SQL problems on GfG Practice: a full catalogue scan found none that accept SQL (the database-style ones accept only Python / pandas).
A22: Per-topic status
A23: # | B23: Section | C23: Topic | D23: Problems | E23: Not available | F23: Gap to 5 | G23: LeetCode | H23: HackerRank | I23: CodeChef | J23: Other verified free options (not counted)
A24: 1 | B24: SQL Basics | C24: SELECT & Column Aliases | D24: =COUNTIFS('Question Bank Details'!$A$2:$A$131,$A24,'Question Bank Details'!$N$2:$N$131,"Yes") -> 5 | E24: =COUNTIFS('Question Bank Details'!$A$2:$A$131,$A24,'Question Bank Details'!$M$2:$M$131,"Not available") -> 0 | F24: =MAX(0,5-D24) -> 0 | G24: =COUNTIFS('Question Bank Details'!$A$2:$A$131,$A24,'Question Bank Details'!$F$2:$F$131,"LeetCode") -> 0 | H24: =COUNTIFS('Question Bank Details'!$A$2:$A$131,$A24,'Question Bank Details'!$F$2:$F$131,"HackerRank") -> 2 | I24: =COUNTIFS('Question Bank Details'!$A$2:$A$131,$A24,'Question Bank Details'!$F$2:$F$131,"CodeChef") -> 3
A25: 2 | B25: SQL Basics | C25: CREATE TABLE & INSERT INTO | D25: =COUNTIFS('Question Bank Details'!$A$2:$A$131,$A25,'Question Bank Details'!$N$2:$N$131,"Yes") -> 5 | E25: =COUNTIFS('Question Bank Details'!$A$2:$A$131,$A25,'Question Bank Details'!$M$2:$M$131,"Not available") -> 0 | F25: =MAX(0,5-D25) -> 0 | G25: =COUNTIFS('Question Bank Details'!$A$2:$A$131,$A25,'Question Bank Details'!$F$2:$F$131,"LeetCode") -> 0 | H25: =COUNTIFS('Question Bank Details'!$A$2:$A$131,$A25,'Question Bank Details'!$F$2:$F$131,"HackerRank") -> 0 | I25: =COUNTIFS('Question Bank Details'!$A$2:$A$131,$A25,'Question Bank Details'!$F$2:$F$131,"CodeChef") -> 5
A26: 3 | B26: SQL Basics | C26: Filtering with WHERE | D26: =COUNTIFS('Question Bank Details'!$A$2:$A$131,$A26,'Question Bank Details'!$N$2:$N$131,"Yes") -> 5 | E26: =COUNTIFS('Question Bank Details'!$A$2:$A$131,$A26,'Question Bank Details'!$M$2:$M$131,"Not available") -> 0 | F26: =MAX(0,5-D26) -> 0 | G26: =COUNTIFS('Question Bank Details'!$A$2:$A$131,$A26,'Question Bank Details'!$F$2:$F$131,"LeetCode") -> 2 | H26: =COUNTIFS('Question Bank Details'!$A$2:$A$131,$A26,'Question Bank Details'!$F$2:$F$131,"HackerRank") -> 1 | I26: =COUNTIFS('Question Bank Details'!$A$2:$A$131,$A26,'Question Bank Details'!$F$2:$F$131,"CodeChef") -> 2 | J26: LeetCode 595 Big Countries; HackerRank Revising the Select Query II, Japanese Cities' Attributes; CodeChef GSQ20 Basic query with Where Clause
A27: 4 | B27: SQL Basics | C27: DISTINCT, ORDER BY & LIMIT | D27: =COUNTIFS('Question Bank Details'!$A$2:$A$131,$A27,'Question Bank Details'!$N$2:$N$131,"Yes") -> 5 | E27: =COUNTIFS('Question Bank Details'!$A$2:$A$131,$A27,'Question Bank Details'!$M$2:$M$131,"Not available") -> 0 | F27: =MAX(0,5-D27) -> 0 | G27: =COUNTIFS('Question Bank Details'!$A$2:$A$131,$A27,'Question Bank Details'!$F$2:$F$131,"LeetCode") -> 1 | H27: =COUNTIFS('Question Bank Details'!$A$2:$A$131,$A27,'Question Bank Details'!$F$2:$F$131,"HackerRank") -> 2 | I27: =COUNTIFS('Question Bank Details'!$A$2:$A$131,$A27,'Question Bank Details'!$F$2:$F$131,"CodeChef") -> 2 | J27: CodeChef SQLPBP08 Salary of Employees (WHERE + ORDER BY DESC), GSQ18 DISTINCT
A28: 5 | B28: SQL Basics | C28: BETWEEN, IN & LIKE | D28: =COUNTIFS('Question Bank Details'!$A$2:$A$131,$A28,'Question Bank Details'!$N$2:$N$131,"Yes") -> 5 | E28: =COUNTIFS('Question Bank Details'!$A$2:$A$131,$A28,'Question Bank Details'!$M$2:$M$131,"Not available") -> 0 | F28: =MAX(0,5-D28) -> 0 | G28: =COUNTIFS('Question Bank Details'!$A$2:$A$131,$A28,'Question Bank Details'!$F$2:$F$131,"LeetCode") -> 1 | H28: =COUNTIFS('Question Bank Details'!$A$2:$A$131,$A28,'Question Bank Details'!$F$2:$F$131,"HackerRank") -> 2 | I28: =COUNTIFS('Question Bank Details'!$A$2:$A$131,$A28,'Question Bank Details'!$F$2:$F$131,"CodeChef") -> 2 | J28: CodeChef SQLPBP15 Locate People (LIKE 'S%'), GSQ25 Like; HackerRank Weather Observation Station 8, 10
A29: 6 | B29: Functions & Aggregation | C29: String Functions | D29: =COUNTIFS('Question Bank Details'!$A$2:$A$131,$A29,'Question Bank Details'!$N$2:$N$131,"Yes") -> 5 | E29: =COUNTIFS('Question Bank Details'!$A$2:$A$131,$A29,'Question Bank Details'!$M$2:$M$131,"Not available") -> 0 | F29: =MAX(0,5-D29) -> 0 | G29: =COUNTIFS('Question Bank Details'!$A$2:$A$131,$A29,'Question Bank Details'!$F$2:$F$131,"LeetCode") -> 3 | H29: =COUNTIFS('Question Bank Details'!$A$2:$A$131,$A29,'Question Bank Details'!$F$2:$F$131,"HackerRank") -> 2 | I29: =COUNTIFS('Question Bank Details'!$A$2:$A$131,$A29,'Question Bank Details'!$F$2:$F$131,"CodeChef") -> 0
A30: 7 | B30: Functions & Aggregation | C30: Aggregate Functions | D30: =COUNTIFS('Question Bank Details'!$A$2:$A$131,$A30,'Question Bank Details'!$N$2:$N$131,"Yes") -> 5 | E30: =COUNTIFS('Question Bank Details'!$A$2:$A$131,$A30,'Question Bank Details'!$M$2:$M$131,"Not available") -> 0 | F30: =MAX(0,5-D30) -> 0 | G30: =COUNTIFS('Question Bank Details'!$A$2:$A$131,$A30,'Question Bank Details'!$F$2:$F$131,"LeetCode") -> 0 | H30: =COUNTIFS('Question Bank Details'!$A$2:$A$131,$A30,'Question Bank Details'!$F$2:$F$131,"HackerRank") -> 2 | I30: =COUNTIFS('Question Bank Details'!$A$2:$A$131,$A30,'Question Bank Details'!$F$2:$F$131,"CodeChef") -> 3 | J30: HackerRank Revising Aggregations - Sum / Averages, Japan Population, Weather Observation Station 4; CodeChef GSQ40
A31: 8 | B31: Functions & Aggregation | C31: Numeric Functions | D31: =COUNTIFS('Question Bank Details'!$A$2:$A$131,$A31,'Question Bank Details'!$N$2:$N$131,"Yes") -> 5 | E31: =COUNTIFS('Question Bank Details'!$A$2:$A$131,$A31,'Question Bank Details'!$M$2:$M$131,"Not available") -> 0 | F31: =MAX(0,5-D31) -> 0 | G31: =COUNTIFS('Question Bank Details'!$A$2:$A$131,$A31,'Question Bank Details'!$F$2:$F$131,"LeetCode") -> 1 | H31: =COUNTIFS('Question Bank Details'!$A$2:$A$131,$A31,'Question Bank Details'!$F$2:$F$131,"HackerRank") -> 3 | I31: =COUNTIFS('Question Bank Details'!$A$2:$A$131,$A31,'Question Bank Details'!$F$2:$F$131,"CodeChef") -> 1 | J31: HackerRank Weather Observation Station 2, 15, 17, 18; CodeChef GSQ58 Debug this query
A32: 9 | B32: Functions & Aggregation | C32: GROUP BY | D32: =COUNTIFS('Question Bank Details'!$A$2:$A$131,$A32,'Question Bank Details'!$N$2:$N$131,"Yes") -> 5 | E32: =COUNTIFS('Question Bank Details'!$A$2:$A$131,$A32,'Question Bank Details'!$M$2:$M$131,"Not available") -> 0 | F32: =MAX(0,5-D32) -> 0 | G32: =COUNTIFS('Question Bank Details'!$A$2:$A$131,$A32,'Question Bank Details'!$F$2:$F$131,"LeetCode") -> 3 | H32: =COUNTIFS('Question Bank Details'!$A$2:$A$131,$A32,'Question Bank Details'!$F$2:$F$131,"HackerRank") -> 1 | I32: =COUNTIFS('Question Bank Details'!$A$2:$A$131,$A32,'Question Bank Details'!$F$2:$F$131,"CodeChef") -> 1 | J32: LeetCode 1693 Daily Leads and Partners, 511 Game Play Analysis I, 1729 Find Followers Count; CodeChef GSQ45 Group By
A33: 10 | B33: Functions & Aggregation | C33: HAVING | D33: =COUNTIFS('Question Bank Details'!$A$2:$A$131,$A33,'Question Bank Details'!$N$2:$N$131,"Yes") -> 5 | E33: =COUNTIFS('Question Bank Details'!$A$2:$A$131,$A33,'Question Bank Details'!$M$2:$M$131,"Not available") -> 0 | F33: =MAX(0,5-D33) -> 0 | G33: =COUNTIFS('Question Bank Details'!$A$2:$A$131,$A33,'Question Bank Details'!$F$2:$F$131,"LeetCode") -> 3 | H33: =COUNTIFS('Question Bank Details'!$A$2:$A$131,$A33,'Question Bank Details'!$F$2:$F$131,"HackerRank") -> 0 | I33: =COUNTIFS('Question Bank Details'!$A$2:$A$131,$A33,'Question Bank Details'!$F$2:$F$131,"CodeChef") -> 2 | J33: CodeChef GSQ59 Debug this code (GROUP BY + HAVING)
A34: 11 | B34: Conditional Logic & Dates | C34: CASE Expressions | D34: =COUNTIFS('Question Bank Details'!$A$2:$A$131,$A34,'Question Bank Details'!$N$2:$N$131,"Yes") -> 5 | E34: =COUNTIFS('Question Bank Details'!$A$2:$A$131,$A34,'Question Bank Details'!$M$2:$M$131,"Not available") -> 0 | F34: =MAX(0,5-D34) -> 0 | G34: =COUNTIFS('Question Bank Details'!$A$2:$A$131,$A34,'Question Bank Details'!$F$2:$F$131,"LeetCode") -> 2 | H34: =COUNTIFS('Question Bank Details'!$A$2:$A$131,$A34,'Question Bank Details'!$F$2:$F$131,"HackerRank") -> 1 | I34: =COUNTIFS('Question Bank Details'!$A$2:$A$131,$A34,'Question Bank Details'!$F$2:$F$131,"CodeChef") -> 2 | J34: CodeChef GSQ82 Count using Case
A35: 12 | B35: Conditional Logic & Dates | C35: Date & Time Functions | D35: =COUNTIFS('Question Bank Details'!$A$2:$A$131,$A35,'Question Bank Details'!$N$2:$N$131,"Yes") -> 5 | E35: =COUNTIFS('Question Bank Details'!$A$2:$A$131,$A35,'Question Bank Details'!$M$2:$M$131,"Not available") -> 0 | F35: =MAX(0,5-D35) -> 0 | G35: =COUNTIFS('Question Bank Details'!$A$2:$A$131,$A35,'Question Bank Details'!$F$2:$F$131,"LeetCode") -> 3 | H35: =COUNTIFS('Question Bank Details'!$A$2:$A$131,$A35,'Question Bank Details'!$F$2:$F$131,"HackerRank") -> 0 | I35: =COUNTIFS('Question Bank Details'!$A$2:$A$131,$A35,'Question Bank Details'!$F$2:$F$131,"CodeChef") -> 2
A36: 13 | B36: Conditional Logic & Dates | C36: Pivoting & Conditional Aggregation | D36: =COUNTIFS('Question Bank Details'!$A$2:$A$131,$A36,'Question Bank Details'!$N$2:$N$131,"Yes") -> 5 | E36: =COUNTIFS('Question Bank Details'!$A$2:$A$131,$A36,'Question Bank Details'!$M$2:$M$131,"Not available") -> 0 | F36: =MAX(0,5-D36) -> 0 | G36: =COUNTIFS('Question Bank Details'!$A$2:$A$131,$A36,'Question Bank Details'!$F$2:$F$131,"LeetCode") -> 4 | H36: =COUNTIFS('Question Bank Details'!$A$2:$A$131,$A36,'Question Bank Details'!$F$2:$F$131,"HackerRank") -> 0 | I36: =COUNTIFS('Question Bank Details'!$A$2:$A$131,$A36,'Question Bank Details'!$F$2:$F$131,"CodeChef") -> 1 | J36: LeetCode 3705 Find Golden Hour Customers, 3497 Analyze Subscription Conversion
A37: 14 | B37: Data Modification & Schema | C37: UPDATE & DELETE | D37: =COUNTIFS('Question Bank Details'!$A$2:$A$131,$A37,'Question Bank Details'!$N$2:$N$131,"Yes") -> 5 | E37: =COUNTIFS('Question Bank Details'!$A$2:$A$131,$A37,'Question Bank Details'!$M$2:$M$131,"Not available") -> 0 | F37: =MAX(0,5-D37) -> 0 | G37: =COUNTIFS('Question Bank Details'!$A$2:$A$131,$A37,'Question Bank Details'!$F$2:$F$131,"LeetCode") -> 1 | H37: =COUNTIFS('Question Bank Details'!$A$2:$A$131,$A37,'Question Bank Details'!$F$2:$F$131,"HackerRank") -> 0 | I37: =COUNTIFS('Question Bank Details'!$A$2:$A$131,$A37,'Question Bank Details'!$F$2:$F$131,"CodeChef") -> 4 | J37: CodeChef GSQ09 update table, GSQ12 Delete From, GSQ55 Update Single Record, RSMSPR05A, RSMSPR07C
A38: 15 | B38: Data Modification & Schema | C38: ALTER TABLE & Constraints | D38: =COUNTIFS('Question Bank Details'!$A$2:$A$131,$A38,'Question Bank Details'!$N$2:$N$131,"Yes") -> 5 | E38: =COUNTIFS('Question Bank Details'!$A$2:$A$131,$A38,'Question Bank Details'!$M$2:$M$131,"Not available") -> 0 | F38: =MAX(0,5-D38) -> 0 | G38: =COUNTIFS('Question Bank Details'!$A$2:$A$131,$A38,'Question Bank Details'!$F$2:$F$131,"LeetCode") -> 0 | H38: =COUNTIFS('Question Bank Details'!$A$2:$A$131,$A38,'Question Bank Details'!$F$2:$F$131,"HackerRank") -> 0 | I38: =COUNTIFS('Question Bank Details'!$A$2:$A$131,$A38,'Question Bank Details'!$F$2:$F$131,"CodeChef") -> 5 | J38: CodeChef SQLKEY01B ON DELETE CASCADE, SQLKEY01C ON DELETE SET NULL, RSMSPR04B, RSMSPR04D, GSQ54
A39: 16 | B39: Joins | C39: INNER JOIN | D39: =COUNTIFS('Question Bank Details'!$A$2:$A$131,$A39,'Question Bank Details'!$N$2:$N$131,"Yes") -> 5 | E39: =COUNTIFS('Question Bank Details'!$A$2:$A$131,$A39,'Question Bank Details'!$M$2:$M$131,"Not available") -> 0 | F39: =MAX(0,5-D39) -> 0 | G39: =COUNTIFS('Question Bank Details'!$A$2:$A$131,$A39,'Question Bank Details'!$F$2:$F$131,"LeetCode") -> 1 | H39: =COUNTIFS('Question Bank Details'!$A$2:$A$131,$A39,'Question Bank Details'!$F$2:$F$131,"HackerRank") -> 3 | I39: =COUNTIFS('Question Bank Details'!$A$2:$A$131,$A39,'Question Bank Details'!$F$2:$F$131,"CodeChef") -> 1 | J39: LeetCode 1075 Project Employees I, 1587 Bank Account Summary II; HackerRank Population Census, Average Population of Each Continent; CodeChef GSQ68A
A40: 17 | B40: Joins | C40: LEFT / RIGHT / FULL OUTER JOIN | D40: =COUNTIFS('Question Bank Details'!$A$2:$A$131,$A40,'Question Bank Details'!$N$2:$N$131,"Yes") -> 5 | E40: =COUNTIFS('Question Bank Details'!$A$2:$A$131,$A40,'Question Bank Details'!$M$2:$M$131,"Not available") -> 0 | F40: =MAX(0,5-D40) -> 0 | G40: =COUNTIFS('Question Bank Details'!$A$2:$A$131,$A40,'Question Bank Details'!$F$2:$F$131,"LeetCode") -> 4 | H40: =COUNTIFS('Question Bank Details'!$A$2:$A$131,$A40,'Question Bank Details'!$F$2:$F$131,"HackerRank") -> 0 | I40: =COUNTIFS('Question Bank Details'!$A$2:$A$131,$A40,'Question Bank Details'!$F$2:$F$131,"CodeChef") -> 1 | J40: LeetCode 1407 Top Travellers, 577 Employee Bonus, 1934 Confirmation Rate; CodeChef GSQ63 Left Joins, GSQ68B
A41: 18 | B41: Joins | C41: SELF JOIN & CROSS JOIN | D41: =COUNTIFS('Question Bank Details'!$A$2:$A$131,$A41,'Question Bank Details'!$N$2:$N$131,"Yes") -> 5 | E41: =COUNTIFS('Question Bank Details'!$A$2:$A$131,$A41,'Question Bank Details'!$M$2:$M$131,"Not available") -> 0 | F41: =MAX(0,5-D41) -> 0 | G41: =COUNTIFS('Question Bank Details'!$A$2:$A$131,$A41,'Question Bank Details'!$F$2:$F$131,"LeetCode") -> 3 | H41: =COUNTIFS('Question Bank Details'!$A$2:$A$131,$A41,'Question Bank Details'!$F$2:$F$131,"HackerRank") -> 1 | I41: =COUNTIFS('Question Bank Details'!$A$2:$A$131,$A41,'Question Bank Details'!$F$2:$F$131,"CodeChef") -> 1 | J41: CodeChef GSQ65 Cross join, GSQ68D; HackerRank Placements; LeetCode 1731
A42: 19 | B42: Subqueries & Set Operations | C42: Subqueries | D42: =COUNTIFS('Question Bank Details'!$A$2:$A$131,$A42,'Question Bank Details'!$N$2:$N$131,"Yes") -> 5 | E42: =COUNTIFS('Question Bank Details'!$A$2:$A$131,$A42,'Question Bank Details'!$M$2:$M$131,"Not available") -> 0 | F42: =MAX(0,5-D42) -> 0 | G42: =COUNTIFS('Question Bank Details'!$A$2:$A$131,$A42,'Question Bank Details'!$F$2:$F$131,"LeetCode") -> 3 | H42: =COUNTIFS('Question Bank Details'!$A$2:$A$131,$A42,'Question Bank Details'!$F$2:$F$131,"HackerRank") -> 1 | I42: =COUNTIFS('Question Bank Details'!$A$2:$A$131,$A42,'Question Bank Details'!$F$2:$F$131,"CodeChef") -> 1 | J42: CodeChef GSQ70 Non-Correlated Subqueries, GSQ74 (labelled 'correlated' but solved with IN); LeetCode 619 Biggest Single Number, 607 Sales Person
A43: 20 | B43: Subqueries & Set Operations | C43: Correlated Subqueries & EXISTS | D43: =COUNTIFS('Question Bank Details'!$A$2:$A$131,$A43,'Question Bank Details'!$N$2:$N$131,"Yes") -> 5 | E43: =COUNTIFS('Question Bank Details'!$A$2:$A$131,$A43,'Question Bank Details'!$M$2:$M$131,"Not available") -> 0 | F43: =MAX(0,5-D43) -> 0 | G43: =COUNTIFS('Question Bank Details'!$A$2:$A$131,$A43,'Question Bank Details'!$F$2:$F$131,"LeetCode") -> 4 | H43: =COUNTIFS('Question Bank Details'!$A$2:$A$131,$A43,'Question Bank Details'!$F$2:$F$131,"HackerRank") -> 1 | I43: =COUNTIFS('Question Bank Details'!$A$2:$A$131,$A43,'Question Bank Details'!$F$2:$F$131,"CodeChef") -> 0 | J43: LeetCode 1174 Immediate Food Delivery II; HackerRank Challenges, 15 Days of Learning SQL (Hard)
A44: 21 | B44: Subqueries & Set Operations | C44: Set Operations | D44: =COUNTIFS('Question Bank Details'!$A$2:$A$131,$A44,'Question Bank Details'!$N$2:$N$131,"Yes") -> 5 | E44: =COUNTIFS('Question Bank Details'!$A$2:$A$131,$A44,'Question Bank Details'!$M$2:$M$131,"Not available") -> 0 | F44: =MAX(0,5-D44) -> 0 | G44: =COUNTIFS('Question Bank Details'!$A$2:$A$131,$A44,'Question Bank Details'!$F$2:$F$131,"LeetCode") -> 3 | H44: =COUNTIFS('Question Bank Details'!$A$2:$A$131,$A44,'Question Bank Details'!$F$2:$F$131,"HackerRank") -> 0 | I44: =COUNTIFS('Question Bank Details'!$A$2:$A$131,$A44,'Question Bank Details'!$F$2:$F$131,"CodeChef") -> 2 | J44: CodeChef GSQ76 Intersect, GSQ68E Union operation; LeetCode 1965 Employees With Missing Information
A45: 22 | B45: Advanced SQL | C45: Common Table Expressions (WITH) | D45: =COUNTIFS('Question Bank Details'!$A$2:$A$131,$A45,'Question Bank Details'!$N$2:$N$131,"Yes") -> 5 | E45: =COUNTIFS('Question Bank Details'!$A$2:$A$131,$A45,'Question Bank Details'!$M$2:$M$131,"Not available") -> 0 | F45: =MAX(0,5-D45) -> 0 | G45: =COUNTIFS('Question Bank Details'!$A$2:$A$131,$A45,'Question Bank Details'!$F$2:$F$131,"LeetCode") -> 2 | H45: =COUNTIFS('Question Bank Details'!$A$2:$A$131,$A45,'Question Bank Details'!$F$2:$F$131,"HackerRank") -> 2 | I45: =COUNTIFS('Question Bank Details'!$A$2:$A$131,$A45,'Question Bank Details'!$F$2:$F$131,"CodeChef") -> 1 | J45: HackerRank Challenges; LeetCode 262 Trips and Users, 1158 Market Analysis I
A46: 23 | B46: Advanced SQL | C46: Window Functions – Ranking | D46: =COUNTIFS('Question Bank Details'!$A$2:$A$131,$A46,'Question Bank Details'!$N$2:$N$131,"Yes") -> 5 | E46: =COUNTIFS('Question Bank Details'!$A$2:$A$131,$A46,'Question Bank Details'!$M$2:$M$131,"Not available") -> 0 | F46: =MAX(0,5-D46) -> 0 | G46: =COUNTIFS('Question Bank Details'!$A$2:$A$131,$A46,'Question Bank Details'!$F$2:$F$131,"LeetCode") -> 2 | H46: =COUNTIFS('Question Bank Details'!$A$2:$A$131,$A46,'Question Bank Details'!$F$2:$F$131,"HackerRank") -> 1 | I46: =COUNTIFS('Question Bank Details'!$A$2:$A$131,$A46,'Question Bank Details'!$F$2:$F$131,"CodeChef") -> 2 | J46: LeetCode 1789 Primary Department for Each Employee, 602 Friend Requests II
A47: 24 | B47: Advanced SQL | C47: Window Functions – LAG / LEAD & Running Totals | D47: =COUNTIFS('Question Bank Details'!$A$2:$A$131,$A47,'Question Bank Details'!$N$2:$N$131,"Yes") -> 5 | E47: =COUNTIFS('Question Bank Details'!$A$2:$A$131,$A47,'Question Bank Details'!$M$2:$M$131,"Not available") -> 0 | F47: =MAX(0,5-D47) -> 0 | G47: =COUNTIFS('Question Bank Details'!$A$2:$A$131,$A47,'Question Bank Details'!$F$2:$F$131,"LeetCode") -> 4 | H47: =COUNTIFS('Question Bank Details'!$A$2:$A$131,$A47,'Question Bank Details'!$F$2:$F$131,"HackerRank") -> 1 | I47: =COUNTIFS('Question Bank Details'!$A$2:$A$131,$A47,'Question Bank Details'!$F$2:$F$131,"CodeChef") -> 0 | J47: LeetCode 3421 Find Students Who Improved, 3580 Find Consistently Improving Employees, 197 Rising Temperature (LAG version)
A48: 25 | B48: Advanced SQL | C48: Recursive CTEs | D48: =COUNTIFS('Question Bank Details'!$A$2:$A$131,$A48,'Question Bank Details'!$N$2:$N$131,"Yes") -> 4 | E48: =COUNTIFS('Question Bank Details'!$A$2:$A$131,$A48,'Question Bank Details'!$M$2:$M$131,"Not available") -> 1 | F48: =MAX(0,5-D48) -> 1 | G48: =COUNTIFS('Question Bank Details'!$A$2:$A$131,$A48,'Question Bank Details'!$F$2:$F$131,"LeetCode") -> 1 | H48: =COUNTIFS('Question Bank Details'!$A$2:$A$131,$A48,'Question Bank Details'!$F$2:$F$131,"HackerRank") -> 3 | I48: =COUNTIFS('Question Bank Details'!$A$2:$A$131,$A48,'Question Bank Details'!$F$2:$F$131,"CodeChef") -> 0
A49: 26 | B49: Advanced SQL | C49: Stored Functions & Procedures | D49: =COUNTIFS('Question Bank Details'!$A$2:$A$131,$A49,'Question Bank Details'!$N$2:$N$131,"Yes") -> 1 | E49: =COUNTIFS('Question Bank Details'!$A$2:$A$131,$A49,'Question Bank Details'!$M$2:$M$131,"Not available") -> 4 | F49: =MAX(0,5-D49) -> 4 | G49: =COUNTIFS('Question Bank Details'!$A$2:$A$131,$A49,'Question Bank Details'!$F$2:$F$131,"LeetCode") -> 1 | H49: =COUNTIFS('Question Bank Details'!$A$2:$A$131,$A49,'Question Bank Details'!$F$2:$F$131,"HackerRank") -> 0 | I49: =COUNTIFS('Question Bank Details'!$A$2:$A$131,$A49,'Question Bank Details'!$F$2:$F$131,"CodeChef") -> 0
C50: Total | D50: =SUM(D24:D49) -> 125 | E50: =SUM(E24:E49) -> 5 | F50: =SUM(F24:F49) -> 5 | G50: =SUM(G24:G49) -> 52 | H50: =SUM(H24:H49) -> 29 | I50: =SUM(I24:I49) -> 44
A52: Slots left empty on purpose (no suitable free problem)
A53: Cell | B53: Topic | D53: Slot | E53: Reason
A54: I26 | B54: Recursive CTEs | D54: Q5 | E54: No fifth free recursive-CTE problem exists on the approved platforms. LeetCode's other hierarchy / recursion problems (1270, 1384, 1613, 1635, 1767) are Premium; CodeChef's free SQL lessons have no recursive queries; the remaining HackerRank SQL challenges do not need recursion; Codeforces and GeeksforGeeks Practice have no SQL problems.
A55: F27 | B55: Stored Functions & Procedures | D55: Q2 | E55: LeetCode 177 is the only free problem that asks for a stored function. LeetCode's stored-procedure problems (2252 Dynamic Pivoting of a Table, 2253 Dynamic Unpivoting of a Table) are Premium; HackerRank and the free CodeChef SQL lessons have no CREATE FUNCTION / PROCEDURE tasks (CodeChef's Transactions lesson is Pro); Codeforces and GeeksforGeeks Practice have no SQL problems.
A56: G27 | B56: Stored Functions & Procedures | D56: Q3 | E56: LeetCode 177 is the only free problem that asks for a stored function. LeetCode's stored-procedure problems (2252 Dynamic Pivoting of a Table, 2253 Dynamic Unpivoting of a Table) are Premium; HackerRank and the free CodeChef SQL lessons have no CREATE FUNCTION / PROCEDURE tasks (CodeChef's Transactions lesson is Pro); Codeforces and GeeksforGeeks Practice have no SQL problems.
A57: H27 | B57: Stored Functions & Procedures | D57: Q4 | E57: LeetCode 177 is the only free problem that asks for a stored function. LeetCode's stored-procedure problems (2252 Dynamic Pivoting of a Table, 2253 Dynamic Unpivoting of a Table) are Premium; HackerRank and the free CodeChef SQL lessons have no CREATE FUNCTION / PROCEDURE tasks (CodeChef's Transactions lesson is Pro); Codeforces and GeeksforGeeks Practice have no SQL problems.
A58: I27 | B58: Stored Functions & Procedures | D58: Q5 | E58: LeetCode 177 is the only free problem that asks for a stored function. LeetCode's stored-procedure problems (2252 Dynamic Pivoting of a Table, 2253 Dynamic Unpivoting of a Table) are Premium; HackerRank and the free CodeChef SQL lessons have no CREATE FUNCTION / PROCEDURE tasks (CodeChef's Transactions lesson is Pro); Codeforces and GeeksforGeeks Practice have no SQL problems.
A60: How each problem was checked
A61: • | B61: Existence, title, difficulty and access were read from each platform's own problem data: LeetCode (GraphQL, including the Premium flag), HackerRank (challenge API) and CodeChef (problem API plus the course / practice-path syllabus, which marks Pro-only lessons).
A62: • | B62: Topic fit was judged from the statement and, where the platform publishes one, the reference solution – i.e. the minimum SQL a correct answer needs – not from titles or tags.
A63: • | B63: Codeforces and GeeksforGeeks Practice were searched as well; neither has SQL problems, so all problems come from LeetCode, HackerRank and CodeChef.
A64: • | B64: Free access means the statement opens without login and the problem is not Premium / Pro-only; submitting needs a free account on every platform.
A65: • | B65: Multiple-choice and 'rearrange the query' items on CodeChef were excluded – only problems where you write and submit a query are listed.
A67: Assumptions about the teaching sequence
A68: • | B68: Topics are taught in the order shown. A problem may use its own topic and any earlier topic, never a later one (e.g. no JOINs before Topic 16, no window functions before Topic 23).
A69: • | B69: Table creation (Topic 2) is taught right after SELECT, because the CodeChef lessons for it finish by displaying the table with SELECT *.
A70: • | B70: Topic 11 (CASE) includes CASE inside an aggregate; Topic 13 then uses that idea for full pivot and percentage reports.
A71: • | B71: Difficulty shows the level within the topic (Easy / Medium / Challenging) with the platform's own label in brackets.
A73: SQL engines
A74: • | B74: LeetCode: MySQL, MS SQL Server, Oracle, PostgreSQL. HackerRank: MySQL, MS SQL Server, Oracle, DB2 (a few challenges omit DB2).
A75: • | B75: CodeChef 'Learn SQL' and 'Learn Advanced SQL' lessons run on SQLite (dates use strftime / JULIANDAY). The 'SQL Practice Queries' path uses MySQL syntax.
A76: • | B76: For HackerRank window-function and recursive problems, pick an engine that supports them (MS SQL Server always does).
A78: Legend for 'SQL Practice Links'
B79: LeetCode | C79: LeetCode Database problem (free).
B80: HackerRank | C80: HackerRank SQL challenge (free).
B81: CodeChef | C81: CodeChef SQL lesson or practice problem (free, non-Pro).
B82: Not available – see Validation Report | C82: No suitable free problem exists for this slot (reasons above).
